Workbook

Sheet Read Me
A1: CIS Critical Security Controls v8.1 — IG3 mapped to Microsoft / Azure / M365
A3: Scope
A4: Implementation Group 3 includes every safeguard in CIS Controls v8.1, so all 18 Controls / 153 Safeguards are mapped. IG1/IG2 columns show which safeguards also belong to the lower groups, so the same sheet can be filtered to IG1 or IG2.
A6: How to use
A7: 1. 'CIS IG3 Mapping' — one row per safeguard: CIS attributes, Microsoft coverage rating, Microsoft services, what to implement, evidence for auditors, licensing notes and related Microsoft Cloud Security Benchmark (MCSB) controls.
A8: 2. Yellow columns (Status, Owner, Target date, Notes) are for you to fill in. Status uses a dropdown: Not started / Planned / In progress / Implemented / Risk accepted / Not applicable. Example: Status = In progress, Owner = Endpoint team, Target date = 2026-12-31, Notes = 'ASR rules in audit; enforce after pilot'.
A9: 3. 'Summary' — counts by Control and coverage rating, plus your implementation progress (calculated from the Status column).
A11: Coverage rating (Microsoft tooling)
A12: Native — Microsoft/Azure/M365 tooling can implement the safeguard technically end-to-end with the right licences.
A13: Partial — Microsoft tooling covers a meaningful part but you need process work, non-Microsoft devices/vendors, or a third party (e.g. pentesters, NAC, physical network gear).
A14: Process — the safeguard is primarily a documented policy/process; Microsoft tools only host evidence or support it.
A16: Important caveats
... A20: • Purview Compliance Manager offers regulatory templates for many standards; check its regulations list for a CIS Controls template to track this programme with continuous assessment.

Sheet Summary
A1: CIS v8.1 IG3 → Microsoft coverage summary
A2: All figures are formulas over the 'CIS IG3 Mapping' sheet and update as you fill in Status.
A4: Control | B4: Control Title | C4: Safeguards | D4: IG1 | E4: IG2 | F4: Native | G4: Partial | H4: Process | I4: Implemented | J4: In progress / Planned | K4: Not started / blank | L4: % Implemented
A5: 1 | B5: Inventory and Control of Enterprise Assets | C5: =COUNTIF('CIS IG3 Mapping'!$A$2:$A$154,A5) -> 5 | D5: =COUNTIFS('CIS IG3 Mapping'!$A$2:$A$154,A5,'CIS IG3 Mapping'!$G$2:$G$154,"✓") -> 2 | E5: =COUNTIFS('CIS IG3 Mapping'!$A$2:$A$154,A5,'CIS IG3 Mapping'!$H$2:$H$154,"✓") -> 4 | F5: =COUNTIFS('CIS IG3 Mapping'!$A$2:$A$154,A5,'CIS IG3 Mapping'!$J$2:$J$154,"Native") -> 4 | G5: =COUNTIFS('CIS IG3 Mapping'!$A$2:$A$154,A5,'CIS IG3 Mapping'!$J$2:$J$154,"Partial") -> 1 | H5: =COUNTIFS('CIS IG3 Mapping'!$A$2:$A$154,A5,'CIS IG3 Mapping'!$J$2:$J$154,"Process") -> 0 | I5: =COUNTIFS('CIS IG3 Mapping'!$A$2:$A$154,A5,'CIS IG3 Mapping'!$P$2:$P$154,"Implemented") -> 0 | J5: =COUNTIFS('CIS IG3 Mapping'!$A$2:$A$154,A5,'CIS IG3 Mapping'!$P$2:$P$154,"In progress")+COUNTIFS('CIS IG3 Mapping'!$A$2:$A$154,A5,'CIS IG3 Mapping'!$P$2:$P$154,"Planned") -> 0 | K5: =COUNTIFS('CIS IG3 Mapping'!$A$2:$A$154,A5,'CIS IG3 Mapping'!$P$2:$P$154,"Not started")+COUNTIFS('CIS IG3 Mapping'!$A$2:$A$154,A5,'CIS IG3 Mapping'!$P$2:$P$154,"") -> 5 | L5: =IF((C5-COUNTIFS('CIS IG3 Mapping'!$A$2:$A$154,A5,'CIS IG3 Mapping'!$P$2:$P$154,"Not applicable"))=0,0,I5/(C5-COUNTIFS('CIS IG3 Mapping'!$A$2:$A$154,A5,'CIS IG3 Mapping'!$P$2:$P$154,"Not applicable"))) -> 0
A6: 2 | B6: Inventory and Control of Software Assets | C6: =COUNTIF('CIS IG3 Mapping'!$A$2:$A$154,A6) -> 7 | D6: =COUNTIFS('CIS IG3 Mapping'!$A$2:$A$154,A6,'CIS IG3 Mapping'!$G$2:$G$154,"✓") -> 3 | E6: =COUNTIFS('CIS IG3 Mapping'!$A$2:$A$154,A6,'CIS IG3 Mapping'!$H$2:$H$154,"✓") -> 6 | F6: =COUNTIFS('CIS IG3 Mapping'!$A$2:$A$154,A6,'CIS IG3 Mapping'!$J$2:$J$154,"Native") -> 7 | G6: =COUNTIFS('CIS IG3 Mapping'!$A$2:$A$154,A6,'CIS IG3 Mapping'!$J$2:$J$154,"Partial") -> 0 | H6: =COUNTIFS('CIS IG3 Mapping'!$A$2:$A$154,A6,'CIS IG3 Mapping'!$J$2:$J$154,"Process") -> 0 | I6: =COUNTIFS('CIS IG3 Mapping'!$A$2:$A$154,A6,'CIS IG3 Mapping'!$P$2:$P$154,"Implemented") -> 0 | J6: =COUNTIFS('CIS IG3 Mapping'!$A$2:$A$154,A6,'CIS IG3 Mapping'!$P$2:$P$154,"In progress")+COUNTIFS('CIS IG3 Mapping'!$A$2:$A$154,A6,'CIS IG3 Mapping'!$P$2:$P$154,"Planned") -> 0 | K6: =COUNTIFS('CIS IG3 Mapping'!$A$2:$A$154,A6,'CIS IG3 Mapping'!$P$2:$P$154,"Not started")+COUNTIFS('CIS IG3 Mapping'!$A$2:$A$154,A6,'CIS IG3 Mapping'!$P$2:$P$154,"") -> 7 | L6: =IF((C6-COUNTIFS('CIS IG3 Mapping'!$A$2:$A$154,A6,'CIS IG3 Mapping'!$P$2:$P$154,"Not applicable"))=0,0,I6/(C6-COUNTIFS('CIS IG3 Mapping'!$A$2:$A$154,A6,'CIS IG3 Mapping'!$P$2:$P$154,"Not applicable"))) -> 0
A7: 3 | B7: Data Protection | C7: =COUNTIF('CIS IG3 Mapping'!$A$2:$A$154,A7) -> 14 | D7: =COUNTIFS('CIS IG3 Mapping'!$A$2:$A$154,A7,'CIS IG3 Mapping'!$G$2:$G$154,"✓") -> 6 | E7: =COUNTIFS('CIS IG3 Mapping'!$A$2:$A$154,A7,'CIS IG3 Mapping'!$H$2:$H$154,"✓") -> 12 | F7: =COUNTIFS('CIS IG3 Mapping'!$A$2:$A$154,A7,'CIS IG3 Mapping'!$J$2:$J$154,"Native") -> 11 | G7: =COUNTIFS('CIS IG3 Mapping'!$A$2:$A$154,A7,'CIS IG3 Mapping'!$J$2:$J$154,"Partial") -> 2 | H7: =COUNTIFS('CIS IG3 Mapping'!$A$2:$A$154,A7,'CIS IG3 Mapping'!$J$2:$J$154,"Process") -> 1 | I7: =COUNTIFS('CIS IG3 Mapping'!$A$2:$A$154,A7,'CIS IG3 Mapping'!$P$2:$P$154,"Implemented") -> 0 | J7: =COUNTIFS('CIS IG3 Mapping'!$A$2:$A$154,A7,'CIS IG3 Mapping'!$P$2:$P$154,"In progress")+COUNTIFS('CIS IG3 Mapping'!$A$2:$A$154,A7,'CIS IG3 Mapping'!$P$2:$P$154,"Planned") -> 0 | K7: =COUNTIFS('CIS IG3 Mapping'!$A$2:$A$154,A7,'CIS IG3 Mapping'!$P$2:$P$154,"Not started")+COUNTIFS('CIS IG3 Mapping'!$A$2:$A$154,A7,'CIS IG3 Mapping'!$P$2:$P$154,"") -> 14 | L7: =IF((C7-COUNTIFS('CIS IG3 Mapping'!$A$2:$A$154,A7,'CIS IG3 Mapping'!$P$2:$P$154,"Not applicable"))=0,0,I7/(C7-COUNTIFS('CIS IG3 Mapping'!$A$2:$A$154,A7,'CIS IG3 Mapping'!$P$2:$P$154,"Not applicable"))) -> 0
A8: 4 | B8: Secure Configuration of Enterprise Assets and Software | C8: =COUNTIF('CIS IG3 Mapping'!$A$2:$A$154,A8) -> 12 | D8: =COUNTIFS('CIS IG3 Mapping'!$A$2:$A$154,A8,'CIS IG3 Mapping'!$G$2:$G$154,"✓") -> 7 | E8: =COUNTIFS('CIS IG3 Mapping'!$A$2:$A$154,A8,'CIS IG3 Mapping'!$H$2:$H$154,"✓") -> 11 | F8: =COUNTIFS('CIS IG3 Mapping'!$A$2:$A$154,A8,'CIS IG3 Mapping'!$J$2:$J$154,"Native") -> 11 | G8: =COUNTIFS('CIS IG3 Mapping'!$A$2:$A$154,A8,'CIS IG3 Mapping'!$J$2:$J$154,"Partial") -> 1 | H8: =COUNTIFS('CIS IG3 Mapping'!$A$2:$A$154,A8,'CIS IG3 Mapping'!$J$2:$J$154,"Process") -> 0 | I8: =COUNTIFS('CIS IG3 Mapping'!$A$2:$A$154,A8,'CIS IG3 Mapping'!$P$2:$P$154,"Implemented") -> 0 | J8: =COUNTIFS('CIS IG3 Mapping'!$A$2:$A$154,A8,'CIS IG3 Mapping'!$P$2:$P$154,"In progress")+COUNTIFS('CIS IG3 Mapping'!$A$2:$A$154,A8,'CIS IG3 Mapping'!$P$2:$P$154,"Planned") -> 0 | K8: =COUNTIFS('CIS IG3 Mapping'!$A$2:$A$154,A8,'CIS IG3 Mapping'!$P$2:$P$154,"Not started")+COUNTIFS('CIS IG3 Mapping'!$A$2:$A$154,A8,'CIS IG3 Mapping'!$P$2:$P$154,"") -> 12 | L8: =IF((C8-COUNTIFS('CIS IG3 Mapping'!$A$2:$A$154,A8,'CIS IG3 Mapping'!$P$2:$P$154,"Not applicable"))=0,0,I8/(C8-COUNTIFS('CIS IG3 Mapping'!$A$2:$A$154,A8,'CIS IG3 Mapping'!$P$2:$P$154,"Not applicable"))) -> 0
A9: 5 | B9: Account Management | C9: =COUNTIF('CIS IG3 Mapping'!$A$2:$A$154,A9) -> 6 | D9: =COUNTIFS('CIS IG3 Mapping'!$A$2:$A$154,A9,'CIS IG3 Mapping'!$G$2:$G$154,"✓") -> 4 | E9: =COUNTIFS('CIS IG3 Mapping'!$A$2:$A$154,A9,'CIS IG3 Mapping'!$H$2:$H$154,"✓") -> 6 | F9: =COUNTIFS('CIS IG3 Mapping'!$A$2:$A$154,A9,'CIS IG3 Mapping'!$J$2:$J$154,"Native") -> 6 | G9: =COUNTIFS('CIS IG3 Mapping'!$A$2:$A$154,A9,'CIS IG3 Mapping'!$J$2:$J$154,"Partial") -> 0 | H9: =COUNTIFS('CIS IG3 Mapping'!$A$2:$A$154,A9,'CIS IG3 Mapping'!$J$2:$J$154,"Process") -> 0 | I9: =COUNTIFS('CIS IG3 Mapping'!$A$2:$A$154,A9,'CIS IG3 Mapping'!$P$2:$P$154,"Implemented") -> 0 | J9: =COUNTIFS('CIS IG3 Mapping'!$A$2:$A$154,A9,'CIS IG3 Mapping'!$P$2:$P$154,"In progress")+COUNTIFS('CIS IG3 Mapping'!$A$2:$A$154,A9,'CIS IG3 Mapping'!$P$2:$P$154,"Planned") -> 0 | K9: =COUNTIFS('CIS IG3 Mapping'!$A$2:$A$154,A9,'CIS IG3 Mapping'!$P$2:$P$154,"Not started")+COUNTIFS('CIS IG3 Mapping'!$A$2:$A$154,A9,'CIS IG3 Mapping'!$P$2:$P$154,"") -> 6 | L9: =IF((C9-COUNTIFS('CIS IG3 Mapping'!$A$2:$A$154,A9,'CIS IG3 Mapping'!$P$2:$P$154,"Not applicable"))=0,0,I9/(C9-COUNTIFS('CIS IG3 Mapping'!$A$2:$A$154,A9,'CIS IG3 Mapping'!$P$2:$P$154,"Not applicable"))) -> 0
A10: 6 | B10: Access Control Management | C10: =COUNTIF('CIS IG3 Mapping'!$A$2:$A$154,A10) -> 8 | D10: =COUNTIFS('CIS IG3 Mapping'!$A$2:$A$154,A10,'CIS IG3 Mapping'!$G$2:$G$154,"✓") -> 5 | E10: =COUNTIFS('CIS IG3 Mapping'!$A$2:$A$154,A10,'CIS IG3 Mapping'!$H$2:$H$154,"✓") -> 7 | F10: =COUNTIFS('CIS IG3 Mapping'!$A$2:$A$154,A10,'CIS IG3 Mapping'!$J$2:$J$154,"Native") -> 7 | G10: =COUNTIFS('CIS IG3 Mapping'!$A$2:$A$154,A10,'CIS IG3 Mapping'!$J$2:$J$154,"Partial") -> 1 | H10: =COUNTIFS('CIS IG3 Mapping'!$A$2:$A$154,A10,'CIS IG3 Mapping'!$J$2:$J$154,"Process") -> 0 | I10: =COUNTIFS('CIS IG3 Mapping'!$A$2:$A$154,A10,'CIS IG3 Mapping'!$P$2:$P$154,"Implemented") -> 0 | J10: =COUNTIFS('CIS IG3 Mapping'!$A$2:$A$154,A10,'CIS IG3 Mapping'!$P$2:$P$154,"In progress")+COUNTIFS('CIS IG3 Mapping'!$A$2:$A$154,A10,'CIS IG3 Mapping'!$P$2:$P$154,"Planned") -> 0 | K10: =COUNTIFS('CIS IG3 Mapping'!$A$2:$A$154,A10,'CIS IG3 Mapping'!$P$2:$P$154,"Not started")+COUNTIFS('CIS IG3 Mapping'!$A$2:$A$154,A10,'CIS IG3 Mapping'!$P$2:$P$154,"") -> 8 | L10: =IF((C10-COUNTIFS('CIS IG3 Mapping'!$A$2:$A$154,A10,'CIS IG3 Mapping'!$P$2:$P$154,"Not applicable"))=0,0,I10/(C10-COUNTIFS('CIS IG3 Mapping'!$A$2:$A$154,A10,'CIS IG3 Mapping'!$P$2:$P$154,"Not applicable"))) -> 0
A11: 7 | B11: Continuous Vulnerability Management | C11: =COUNTIF('CIS IG3 Mapping'!$A$2:$A$154,A11) -> 7 | D11: =COUNTIFS('CIS IG3 Mapping'!$A$2:$A$154,A11,'CIS IG3 Mapping'!$G$2:$G$154,"✓") -> 4 | E11: =COUNTIFS('CIS IG3 Mapping'!$A$2:$A$154,A11,'CIS IG3 Mapping'!$H$2:$H$154,"✓") -> 7 | F11: =COUNTIFS('CIS IG3 Mapping'!$A$2:$A$154,A11,'CIS IG3 Mapping'!$J$2:$J$154,"Native") -> 5 | G11: =COUNTIFS('CIS IG3 Mapping'!$A$2:$A$154,A11,'CIS IG3 Mapping'!$J$2:$J$154,"Partial") -> 1 | H11: =COUNTIFS('CIS IG3 Mapping'!$A$2:$A$154,A11,'CIS IG3 Mapping'!$J$2:$J$154,"Process") -> 1 | I11: =COUNTIFS('CIS IG3 Mapping'!$A$2:$A$154,A11,'CIS IG3 Mapping'!$P$2:$P$154,"Implemented") -> 0 | J11: =COUNTIFS('CIS IG3 Mapping'!$A$2:$A$154,A11,'CIS IG3 Mapping'!$P$2:$P$154,"In progress")+COUNTIFS('CIS IG3 Mapping'!$A$2:$A$154,A11,'CIS IG3 Mapping'!$P$2:$P$154,"Planned") -> 0 | K11: =COUNTIFS('CIS IG3 Mapping'!$A$2:$A$154,A11,'CIS IG3 Mapping'!$P$2:$P$154,"Not started")+COUNTIFS('CIS IG3 Mapping'!$A$2:$A$154,A11,'CIS IG3 Mapping'!$P$2:$P$154,"") -> 7 | L11: =IF((C11-COUNTIFS('CIS IG3 Mapping'!$A$2:$A$154,A11,'CIS IG3 Mapping'!$P$2:$P$154,"Not applicable"))=0,0,I11/(C11-COUNTIFS('CIS IG3 Mapping'!$A$2:$A$154,A11,'CIS IG3 Mapping'!$P$2:$P$154,"Not applicable"))) -> 0
A12: 8 | B12: Audit Log Management | C12: =COUNTIF('CIS IG3 Mapping'!$A$2:$A$154,A12) -> 12 | D12: =COUNTIFS('CIS IG3 Mapping'!$A$2:$A$154,A12,'CIS IG3 Mapping'!$G$2:$G$154,"✓") -> 3 | E12: =COUNTIFS('CIS IG3 Mapping'!$A$2:$A$154,A12,'CIS IG3 Mapping'!$H$2:$H$154,"✓") -> 11 | F12: =COUNTIFS('CIS IG3 Mapping'!$A$2:$A$154,A12,'CIS IG3 Mapping'!$J$2:$J$154,"Native") -> 11 | G12: =COUNTIFS('CIS IG3 Mapping'!$A$2:$A$154,A12,'CIS IG3 Mapping'!$J$2:$J$154,"Partial") -> 0 | H12: =COUNTIFS('CIS IG3 Mapping'!$A$2:$A$154,A12,'CIS IG3 Mapping'!$J$2:$J$154,"Process") -> 1 | I12: =COUNTIFS('CIS IG3 Mapping'!$A$2:$A$154,A12,'CIS IG3 Mapping'!$P$2:$P$154,"Implemented") -> 0 | J12: =COUNTIFS('CIS IG3 Mapping'!$A$2:$A$154,A12,'CIS IG3 Mapping'!$P$2:$P$154,"In progress")+COUNTIFS('CIS IG3 Mapping'!$A$2:$A$154,A12,'CIS IG3 Mapping'!$P$2:$P$154,"Planned") -> 0 | K12: =COUNTIFS('CIS IG3 Mapping'!$A$2:$A$154,A12,'CIS IG3 Mapping'!$P$2:$P$154,"Not started")+COUNTIFS('CIS IG3 Mapping'!$A$2:$A$154,A12,'CIS IG3 Mapping'!$P$2:$P$154,"") -> 12 | L12: =IF((C12-COUNTIFS('CIS IG3 Mapping'!$A$2:$A$154,A12,'CIS IG3 Mapping'!$P$2:$P$154,"Not applicable"))=0,0,I12/(C12-COUNTIFS('CIS IG3 Mapping'!$A$2:$A$154,A12,'CIS IG3 Mapping'!$P$2:$P$154,"Not applicable"))) -> 0
A13: 9 | B13: Email and Web Browser Protections | C13: =COUNTIF('CIS IG3 Mapping'!$A$2:$A$154,A13) -> 7 | D13: =COUNTIFS('CIS IG3 Mapping'!$A$2:$A$154,A13,'CIS IG3 Mapping'!$G$2:$G$154,"✓") -> 2 | E13: =COUNTIFS('CIS IG3 Mapping'!$A$2:$A$154,A13,'CIS IG3 Mapping'!$H$2:$H$154,"✓") -> 6 | F13: =COUNTIFS('CIS IG3 Mapping'!$A$2:$A$154,A13,'CIS IG3 Mapping'!$J$2:$J$154,"Native") -> 7 | G13: =COUNTIFS('CIS IG3 Mapping'!$A$2:$A$154,A13,'CIS IG3 Mapping'!$J$2:$J$154,"Partial") -> 0 | H13: =COUNTIFS('CIS IG3 Mapping'!$A$2:$A$154,A13,'CIS IG3 Mapping'!$J$2:$J$154,"Process") -> 0 | I13: =COUNTIFS('CIS IG3 Mapping'!$A$2:$A$154,A13,'CIS IG3 Mapping'!$P$2:$P$154,"Implemented") -> 0 | J13: =COUNTIFS('CIS IG3 Mapping'!$A$2:$A$154,A13,'CIS IG3 Mapping'!$P$2:$P$154,"In progress")+COUNTIFS('CIS IG3 Mapping'!$A$2:$A$154,A13,'CIS IG3 Mapping'!$P$2:$P$154,"Planned") -> 0 | K13: =COUNTIFS('CIS IG3 Mapping'!$A$2:$A$154,A13,'CIS IG3 Mapping'!$P$2:$P$154,"Not started")+COUNTIFS('CIS IG3 Mapping'!$A$2:$A$154,A13,'CIS IG3 Mapping'!$P$2:$P$154,"") -> 7 | L13: =IF((C13-COUNTIFS('CIS IG3 Mapping'!$A$2:$A$154,A13,'CIS IG3 Mapping'!$P$2:$P$154,"Not applicable"))=0,0,I13/(C13-COUNTIFS('CIS IG3 Mapping'!$A$2:$A$154,A13,'CIS IG3 Mapping'!$P$2:$P$154,"Not applicable"))) -> 0
A14: 10 | B14: Malware Defenses | C14: =COUNTIF('CIS IG3 Mapping'!$A$2:$A$154,A14) -> 7 | D14: =COUNTIFS('CIS IG3 Mapping'!$A$2:$A$154,A14,'CIS IG3 Mapping'!$G$2:$G$154,"✓") -> 3 | E14: =COUNTIFS('CIS IG3 Mapping'!$A$2:$A$154,A14,'CIS IG3 Mapping'!$H$2:$H$154,"✓") -> 7 | F14: =COUNTIFS('CIS IG3 Mapping'!$A$2:$A$154,A14,'CIS IG3 Mapping'!$J$2:$J$154,"Native") -> 7 | G14: =COUNTIFS('CIS IG3 Mapping'!$A$2:$A$154,A14,'CIS IG3 Mapping'!$J$2:$J$154,"Partial") -> 0 | H14: =COUNTIFS('CIS IG3 Mapping'!$A$2:$A$154,A14,'CIS IG3 Mapping'!$J$2:$J$154,"Process") -> 0 | I14: =COUNTIFS('CIS IG3 Mapping'!$A$2:$A$154,A14,'CIS IG3 Mapping'!$P$2:$P$154,"Implemented") -> 0 | J14: =COUNTIFS('CIS IG3 Mapping'!$A$2:$A$154,A14,'CIS IG3 Mapping'!$P$2:$P$154,"In progress")+COUNTIFS('CIS IG3 Mapping'!$A$2:$A$154,A14,'CIS IG3 Mapping'!$P$2:$P$154,"Planned") -> 0 | K14: =COUNTIFS('CIS IG3 Mapping'!$A$2:$A$154,A14,'CIS IG3 Mapping'!$P$2:$P$154,"Not started")+COUNTIFS('CIS IG3 Mapping'!$A$2:$A$154,A14,'CIS IG3 Mapping'!$P$2:$P$154,"") -> 7 | L14: =IF((C14-COUNTIFS('CIS IG3 Mapping'!$A$2:$A$154,A14,'CIS IG3 Mapping'!$P$2:$P$154,"Not applicable"))=0,0,I14/(C14-COUNTIFS('CIS IG3 Mapping'!$A$2:$A$154,A14,'CIS IG3 Mapping'!$P$2:$P$154,"Not applicable"))) -> 0
A15: 11 | B15: Data Recovery | C15: =COUNTIF('CIS IG3 Mapping'!$A$2:$A$154,A15) -> 5 | D15: =COUNTIFS('CIS IG3 Mapping'!$A$2:$A$154,A15,'CIS IG3 Mapping'!$G$2:$G$154,"✓") -> 4 | E15: =COUNTIFS('CIS IG3 Mapping'!$A$2:$A$154,A15,'CIS IG3 Mapping'!$H$2:$H$154,"✓") -> 5 | F15: =COUNTIFS('CIS IG3 Mapping'!$A$2:$A$154,A15,'CIS IG3 Mapping'!$J$2:$J$154,"Native") -> 4 | G15: =COUNTIFS('CIS IG3 Mapping'!$A$2:$A$154,A15,'CIS IG3 Mapping'!$J$2:$J$154,"Partial") -> 0 | H15: =COUNTIFS('CIS IG3 Mapping'!$A$2:$A$154,A15,'CIS IG3 Mapping'!$J$2:$J$154,"Process") -> 1 | I15: =COUNTIFS('CIS IG3 Mapping'!$A$2:$A$154,A15,'CIS IG3 Mapping'!$P$2:$P$154,"Implemented") -> 0 | J15: =COUNTIFS('CIS IG3 Mapping'!$A$2:$A$154,A15,'CIS IG3 Mapping'!$P$2:$P$154,"In progress")+COUNTIFS('CIS IG3 Mapping'!$A$2:$A$154,A15,'CIS IG3 Mapping'!$P$2:$P$154,"Planned") -> 0 | K15: =COUNTIFS('CIS IG3 Mapping'!$A$2:$A$154,A15,'CIS IG3 Mapping'!$P$2:$P$154,"Not started")+COUNTIFS('CIS IG3 Mapping'!$A$2:$A$154,A15,'CIS IG3 Mapping'!$P$2:$P$154,"") -> 5 | L15: =IF((C15-COUNTIFS('CIS IG3 Mapping'!$A$2:$A$154,A15,'CIS IG3 Mapping'!$P$2:$P$154,"Not applicable"))=0,0,I15/(C15-COUNTIFS('CIS IG3 Mapping'!$A$2:$A$154,A15,'CIS IG3 Mapping'!$P$2:$P$154,"Not applicable"))) -> 0
A16: 12 | B16: Network Infrastructure Management | C16: =COUNTIF('CIS IG3 Mapping'!$A$2:$A$154,A16) -> 8 | D16: =COUNTIFS('CIS IG3 Mapping'!$A$2:$A$154,A16,'CIS IG3 Mapping'!$G$2:$G$154,"✓") -> 1 | E16: =COUNTIFS('CIS IG3 Mapping'!$A$2:$A$154,A16,'CIS IG3 Mapping'!$H$2:$H$154,"✓") -> 7 | F16: =COUNTIFS('CIS IG3 Mapping'!$A$2:$A$154,A16,'CIS IG3 Mapping'!$J$2:$J$154,"Native") -> 6 | G16: =COUNTIFS('CIS IG3 Mapping'!$A$2:$A$154,A16,'CIS IG3 Mapping'!$J$2:$J$154,"Partial") -> 2 | H16: =COUNTIFS('CIS IG3 Mapping'!$A$2:$A$154,A16,'CIS IG3 Mapping'!$J$2:$J$154,"Process") -> 0 | I16: =COUNTIFS('CIS IG3 Mapping'!$A$2:$A$154,A16,'CIS IG3 Mapping'!$P$2:$P$154,"Implemented") -> 0 | J16: =COUNTIFS('CIS IG3 Mapping'!$A$2:$A$154,A16,'CIS IG3 Mapping'!$P$2:$P$154,"In progress")+COUNTIFS('CIS IG3 Mapping'!$A$2:$A$154,A16,'CIS IG3 Mapping'!$P$2:$P$154,"Planned") -> 0 | K16: =COUNTIFS('CIS IG3 Mapping'!$A$2:$A$154,A16,'CIS IG3 Mapping'!$P$2:$P$154,"Not started")+COUNTIFS('CIS IG3 Mapping'!$A$2:$A$154,A16,'CIS IG3 Mapping'!$P$2:$P$154,"") -> 8 | L16: =IF((C16-COUNTIFS('CIS IG3 Mapping'!$A$2:$A$154,A16,'CIS IG3 Mapping'!$P$2:$P$154,"Not applicable"))=0,0,I16/(C16-COUNTIFS('CIS IG3 Mapping'!$A$2:$A$154,A16,'CIS IG3 Mapping'!$P$2:$P$154,"Not applicable"))) -> 0
... A22: 18 | B22: Penetration Testing | C22: =COUNTIF('CIS IG3 Mapping'!$A$2:$A$154,A22) -> 5 | D22: =COUNTIFS('CIS IG3 Mapping'!$A$2:$A$154,A22,'CIS IG3 Mapping'!$G$2:$G$154,"✓") -> 0 | E22: =COUNTIFS('CIS IG3 Mapping'!$A$2:$A$154,A22,'CIS IG3 Mapping'!$H$2:$H$154,"✓") -> 3 | F22: =COUNTIFS('CIS IG3 Mapping'!$A$2:$A$154,A22,'CIS IG3 Mapping'!$J$2:$J$154,"Native") -> 2 | G22: =COUNTIFS('CIS IG3 Mapping'!$A$2:$A$154,A22,'CIS IG3 Mapping'!$J$2:$J$154,"Partial") -> 2 | H22: =COUNTIFS('CIS IG3 Mapping'!$A$2:$A$154,A22,'CIS IG3 Mapping'!$J$2:$J$154,"Process") -> 1 | I22: =COUNTIFS('CIS IG3 Mapping'!$A$2:$A$154,A22,'CIS IG3 Mapping'!$P$2:$P$154,"Implemented") -> 0 | J22: =COUNTIFS('CIS IG3 Mapping'!$A$2:$A$154,A22,'CIS IG3 Mapping'!$P$2:$P$154,"In progress")+COUNTIFS('CIS IG3 Mapping'!$A$2:$A$154,A22,'CIS IG3 Mapping'!$P$2:$P$154,"Planned") -> 0 | K22: =COUNTIFS('CIS IG3 Mapping'!$A$2:$A$154,A22,'CIS IG3 Mapping'!$P$2:$P$154,"Not started")+COUNTIFS('CIS IG3 Mapping'!$A$2:$A$154,A22,'CIS IG3 Mapping'!$P$2:$P$154,"") -> 5 | L22: =IF((C22-COUNTIFS('CIS IG3 Mapping'!$A$2:$A$154,A22,'CIS IG3 Mapping'!$P$2:$P$154,"Not applicable"))=0,0,I22/(C22-COUNTIFS('CIS IG3 Mapping'!$A$2:$A$154,A22,'CIS IG3 Mapping'!$P$2:$P$154,"Not applicable"))) -> 0
B23: Total | C23: =SUM(C5:C22) -> 153 | D23: =SUM(D5:D22) -> 56 | E23: =SUM(E5:E22) -> 130 | F23: =SUM(F5:F22) -> 108 | G23: =SUM(G5:G22) -> 29 | H23: =SUM(H5:H22) -> 16 | I23: =SUM(I5:I22) -> 0 | J23: =SUM(J5:J22) -> 0 | K23: =SUM(K5:K22) -> 153 | L23: =IF((C23-COUNTIF('CIS IG3 Mapping'!$P$2:$P$154,"Not applicable"))=0,0,I23/(C23-COUNTIF('CIS IG3 Mapping'!$P$2:$P$154,"Not applicable"))) -> 0
A25: % Implemented excludes safeguards marked 'Not applicable'. Coverage ratings: see 'Read Me'.

Sheet CIS IG3 Mapping
A1: Control | B1: Control Title | C1: Safeguard | D1: Safeguard Title | E1: Asset Type | F1: Security Function | G1: IG1 | H1: IG2 | I1: IG3 | J1: Microsoft Coverage | K1: Microsoft / Azure / M365 Services | L1: What to Implement to be Compliant | M1: Evidence for Audit | N1: Licensing Notes | O1: Related MCSB | P1: Status | Q1: Owner | R1: Target Date | S1: Notes
A2: 1 | B2: Inventory and Control of Enterprise Assets | C2: 1.1 | D2: Establish and Maintain a Detailed Enterprise Asset Inventory | E2: Devices | F2: Identify | G2: ✓ | H2: ✓ | I2: ✓ | J2: Native | K2: Intune; Defender for Endpoint (device inventory); Entra ID devices; Azure Resource Graph; Defender for Cloud; Azure Arc | L2: Enrol all Windows/macOS/iOS/Android devices in Intune (Autopilot / auto-enrolment via Entra join). Onboard every endpoint and server to Defender for Endpoint so the Device inventory is authoritative. Onboard on-prem/other-cloud servers via Azure Arc so they appear in Azure Resource Graph. Use tags/device categories for owner, department and criticality. Export Intune + MDE + Resource Graph inventories on a schedule (Graph API / Logic App) into a single register and review at least twice a year. | M2: Intune 'All devices' export; MDE Device inventory; Resource Graph query of all resources; review sign-off record. | N2: Intune (M365 E3/E5 or EMS); MDE P2 for full inventory; Azure Arc free for inventory, paid for extra services. | O2: AM-1
A3: 1 | B3: Inventory and Control of Enterprise Assets | C3: 1.2 | D3: Address Unauthorized Assets | E3: Devices | F3: Respond | G3: ✓ | H3: ✓ | I3: ✓ | J3: Native | K3: Intune compliance policies; Entra Conditional Access; Defender for Endpoint (device discovery, 'unmanaged' status); Network Access Control (3rd party) | L3: Require 'device marked compliant' / 'Entra hybrid joined' in Conditional Access so unmanaged devices cannot reach M365/Azure resources. Review MDE Device inventory 'Onboarding status: Can be onboarded / Unsupported' weekly and either onboard, isolate or remove. Use Intune device clean-up rules to retire stale records. Document the weekly review and disposition (remove/deny/quarantine). | M3: Conditional Access policy export; weekly MDE discovered-device review log; Intune device clean-up rule settings. | N3: Entra ID P1 for Conditional Access; MDE P2. | O3: AM-1, NS-1
A4: 1 | B4: Inventory and Control of Enterprise Assets | C4: 1.3 | D4: Utilize an Active Discovery Tool | E4: Devices | F4: Detect | H4: ✓ | I4: ✓ | J4: Native | K4: Defender for Endpoint device discovery (Standard/active probing); Defender for IoT; Defender External Attack Surface Management | L4: Set MDE Device discovery mode to 'Standard discovery' so onboarded devices actively probe the network. Configure monitored networks and exclusions in Settings > Device discovery. Use Defender for IoT for OT/IoT segments and Defender EASM for internet-facing assets. Run discovery at least daily; feed new findings into the 1.2 process. | M4: MDE Device discovery settings screenshot; discovered-device report; EASM inventory. | N4: MDE P2 / Defender for Business; Defender for IoT and EASM licensed separately. | O4: AM-1
A5: 1 | B5: Inventory and Control of Enterprise Assets | C5: 1.4 | D5: Use DHCP Logging to Update Enterprise Asset Inventory | E5: Devices | F5: Identify | H5: ✓ | I5: ✓ | J5: Partial | K5: Windows Server DHCP audit logs; Azure Monitor Agent + Data Collection Rules; Microsoft Sentinel; (Azure VNets use platform DHCP with no customer logs) | L5: Enable DHCP audit logging on Windows DHCP servers (or your network DHCP appliance). Collect the logs with Azure Monitor Agent / syslog connector into Sentinel. Build a scheduled KQL query that lists MAC/IP/hostname leases not present in the MDE/Intune inventory and raise an incident or update the asset register weekly. In Azure, use NIC/VM inventory from Resource Graph instead because Azure DHCP is platform-managed. | M5: DCR config; Sentinel analytics rule 'DHCP lease not in inventory'; weekly results. | N5: Sentinel / Log Analytics ingestion cost. | O5: AM-1, LT-1
A6: 1 | B6: Inventory and Control of Enterprise Assets | C6: 1.5 | D6: Use a Passive Asset Discovery Tool | E6: Devices | F6: Detect | I6: ✓ | J6: Native | K6: Defender for Endpoint (Basic/passive discovery); Defender for IoT network sensors; Defender for Identity | L6: Keep MDE passive discovery enabled (it is on by default with Standard mode). Deploy Defender for IoT sensors on SPAN/TAP ports in OT, IoT and data-centre segments for passive fingerprinting. Defender for Identity sensors on domain controllers add passive identification of devices authenticating to AD. Review newly discovered assets weekly and update the inventory. | M6: Defender for IoT sensor list and device inventory; MDE discovered devices with 'Discovery source' passive. | N6: MDE P2; Defender for IoT (per-site licence); Defender for Identity (E5 Security). | O6: AM-1, NS-1
A7: 2 | B7: Inventory and Control of Software Assets | C7: 2.1 | D7: Establish and Maintain a Software Inventory | E7: Software | F7: Identify | G7: ✓ | H7: ✓ | I7: ✓ | J7: Native | K7: Defender Vulnerability Management (Software inventory); Intune Discovered apps; Azure Arc / Defender for Servers; Configuration Manager | L7: Use MDE/Defender Vulnerability Management Software inventory as the system of record (publisher, version, install count, end-of-support). Supplement with Intune 'Discovered apps' and Intune app catalogue for business purpose/owner. For servers, onboard Defender for Servers via Arc. Export via Graph/Advanced Hunting (DeviceTvmSoftwareInventory) and add business owner, purpose, approval status. Review every six months. | M7: DVM software inventory export; approved software register with owners and review date. | N7: MDE P2 includes core TVM; DVM add-on / Defender for Servers P2 for full features. | O7: AM-2, AM-5
A8: 2 | B8: Inventory and Control of Software Assets | C8: 2.2 | D8: Ensure Authorized Software is Currently Supported | E8: Software | F8: Identify | G8: ✓ | H8: ✓ | I8: ✓ | J8: Native | K8: Defender Vulnerability Management (end-of-support software & versions); Intune; Azure Advisor / Defender for Cloud | L8: Use DVM 'End of support' filter and the 'Upgrade' security recommendations to identify unsupported apps/OS. Track Windows/Office servicing channels in Intune (Windows Update rings, feature update policies, M365 Apps update channel). Record documented exceptions with compensating controls for anything unsupported that must remain. Review monthly. | M8: DVM EOS report; exception register with compensating controls. | N8: MDE P2 / DVM add-on. | O8: AM-2, PV-6
A9: 2 | B9: Inventory and Control of Software Assets | C9: 2.3 | D9: Address Unauthorized Software | E9: Software | F9: Respond | G9: ✓ | H9: ✓ | I9: ✓ | J9: Native | K9: Defender Vulnerability Management (block vulnerable apps / remediation requests); Intune (uninstall assignments); App Control for Business; Defender for Cloud Apps | L9: Review the software inventory monthly against the approved list. Remove unauthorized software using Intune uninstall assignments or Win32 app with uninstall command, or create DVM remediation requests. Block it from running with App Control for Business / MDE indicators (file hash / certificate). For SaaS, mark unsanctioned apps in Defender for Cloud Apps to block via MDE network protection. | M9: Monthly unauthorized-software review; Intune uninstall assignments; MDE file/cert indicators; MDCA unsanctioned apps list. | N9: MDE P2; Intune; Defender for Cloud Apps (E5). | O9: AM-5
A10: 2 | B10: Inventory and Control of Software Assets | C10: 2.4 | D10: Utilize Automated Software Inventory Tools | E10: Software | F10: Detect | H10: ✓ | I10: ✓ | J10: Native | K10: Defender for Endpoint / DVM; Intune Discovered apps; Defender for Servers (Arc); Azure Update Manager / Change Tracking & Inventory | L10: Ensure 100% of endpoints and servers are onboarded to MDE (sensor collects software inventory continuously). Enable Change Tracking and Inventory on Azure/Arc servers for installed software and service changes. Use Advanced Hunting/Graph to automate the inventory export for 2.1. | M10: Onboarding coverage report (% devices onboarded); Change Tracking workspace data. | N10: MDE P2; Defender for Servers; Log Analytics ingestion. | O10: AM-2
A11: 2 | B11: Inventory and Control of Software Assets | C11: 2.5 | D11: Allowlist Authorized Software | E11: Software | F11: Protect | H11: ✓ | I11: ✓ | J11: Native | K11: App Control for Business (WDAC) via Intune incl. Managed Installer and ISG; AppLocker; Defender for Cloud adaptive application controls (retired - use WDAC); Intune Endpoint Privilege Management | L11: Deploy App Control for Business policies through Intune: start in audit mode, set Intune Management Extension as Managed Installer, optionally trust Intelligent Security Graph, then enforce. Use supplemental policies for line-of-business apps signed with your certificate. Pair with standard-user accounts and Intune Endpoint Privilege Management so users cannot install unapproved software. Review policy at least twice a year. | M11: Intune App Control policy (enforced); CodeIntegrity event logs / Advanced Hunting DeviceEvents AppControl*; review records. | N11: Windows Enterprise/Education (E3+) for App Control; EPM needs Intune Suite/add-on. | O11: AM-5, ES-2
A12: 2 | B12: Inventory and Control of Software Assets | C12: 2.6 | D12: Allowlist Authorized Libraries | E12: Software | F12: Protect | H12: ✓ | I12: ✓ | J12: Native | K12: App Control for Business (DLL enforcement); AppLocker DLL rules | L12: Enable DLL/driver enforcement in App Control for Business policies (it covers .dll and .sys files when 'Disabled: Script Enforcement' not set and kernel/user mode rules defined). Allow libraries by publisher signer or hash; test in audit mode before enforcement. For servers, use the same policies via Arc/GPO. | M12: App Control policy XML showing user-mode code integrity & signer rules; audit/enforce event logs. | N12: Windows Enterprise / Server. | O12: AM-5, ES-2
A13: 2 | B13: Inventory and Control of Software Assets | C13: 2.7 | D13: Allowlist Authorized Scripts | E13: Software | F13: Protect | I13: ✓ | J13: Native | K13: App Control for Business script enforcement (PowerShell Constrained Language Mode); Intune script signing; AMSI; ASR rules | L13: Enable script enforcement in App Control so unsigned PowerShell runs in Constrained Language Mode and unapproved .js/.vbs/.ps1 are blocked. Sign approved scripts with an internal code-signing cert and set PowerShell execution policy AllSigned via Intune. Add ASR rules 'Block execution of potentially obfuscated scripts' and 'Block JavaScript or VBScript from launching downloaded executable content'. Keep AMSI enabled. | M13: App Control policy with script enforcement; Intune PowerShell execution policy; ASR rule report. | N13: Windows Enterprise; MDE for ASR reporting. | O13: AM-5, ES-2
A14: 3 | B14: Data Protection | C14: 3.1 | D14: Establish and Maintain a Data Management Process | E14: Data | F14: Govern | G14: ✓ | H14: ✓ | I14: ✓ | J14: Process | K14: Microsoft Purview (Compliance Manager, Information Protection, Data Lifecycle Management); SharePoint policy library | L14: Write and approve a data management policy covering data sensitivity, owners, handling, retention and disposal. Implement it technically through Purview sensitivity labels (3.7), retention policies (3.4) and DLP (3.13). Track the policy as evidence in Compliance Manager and review annually or on significant change. | M14: Approved data management policy; Compliance Manager evidence; annual review record. | N14: Purview features vary by E3/E5. | O14: DP-1, GS-4
A15: 3 | B15: Data Protection | C15: 3.2 | D15: Establish and Maintain a Data Inventory | E15: Data | F15: Identify | G15: ✓ | H15: ✓ | I15: ✓ | J15: Native | K15: Microsoft Purview Data Map / Unified Catalog; Purview Content Explorer & Data Explorer; Defender for Cloud (sensitive data discovery); Data Security Posture Management | L15: Use Purview Content Explorer to inventory sensitive information types and labels across Exchange, SharePoint, OneDrive and Teams. Register Azure data sources (SQL, Storage, Synapse, Fabric) and on-prem sources in Purview Data Map and run classification scans. Enable Defender CSPM sensitive data discovery for storage/databases. Record owners and sensitivity; review annually (prioritise sensitive data). | M15: Purview Data Map scan results; Content Explorer report; data owner register. | N15: Content Explorer needs E5 Compliance; Data Map is pay-as-you-go; Defender CSPM plan. | O15: DP-1
A16: 3 | B16: Data Protection | C16: 3.3 | D16: Configure Data Access Control Lists | E16: Data | F16: Protect | G16: ✓ | H16: ✓ | I16: ✓ | J16: Native | K16: SharePoint/OneDrive permissions & sharing settings; Entra groups; Azure RBAC; Storage/SQL Entra authentication; SharePoint Advanced Management (site access reviews); Entra Access Reviews | L16: Restrict tenant and site-level external sharing; default sharing links to 'Specific people'. Grant access via Entra security groups, not individuals. Use Azure RBAC and Entra-only authentication for Storage, SQL and Key Vault (disable shared keys / SQL auth where possible). Run Entra access reviews on groups/Teams that grant access to sensitive data and SharePoint Advanced Management data access governance reports for overshared sites. | M16: Sharing settings export; RBAC assignments; access review results; oversharing reports. | N16: Access Reviews need Entra ID P2/Governance; SharePoint Advanced Management add-on (included with Copilot). | O16: DP-1, PA-7, IM-1
A17: 3 | B17: Data Protection | C17: 3.4 | D17: Enforce Data Retention | E17: Data | F17: Protect | G17: ✓ | H17: ✓ | I17: ✓ | J17: Native | K17: Purview Data Lifecycle Management / Records Management (retention policies & labels); Azure Storage lifecycle management; Azure SQL long-term retention | L17: Create Purview retention policies per workload (Exchange, SharePoint, OneDrive, Teams) that keep and then delete data per the retention schedule. Use retention labels (auto-apply on SITs/trainable classifiers in E5) for records with specific periods. For Azure data, use Storage lifecycle policies and immutable storage where required. Document minimum and maximum timelines per data class. | M17: Retention policy list and scope; retention schedule document; lifecycle rules. | N17: Basic retention in E3; auto-apply labels and Records Management in E5 Compliance. | O17: DP-1
A18: 3 | B18: Data Protection | C18: 3.5 | D18: Securely Dispose of Data | E18: Data | F18: Protect | G18: ✓ | H18: ✓ | I18: ✓ | J18: Partial | K18: Purview disposition reviews / retention delete; Intune Wipe / Autopilot Reset; BitLocker (crypto-erase); Azure Storage deletion (platform sanitisation) | L18: Use Purview retention with 'delete at end of period' and disposition reviews for records, with proof-of-disposition. Wipe devices with Intune Wipe before reassignment/disposal; BitLocker ensures data is unrecoverable once keys are removed. Microsoft sanitises Azure/M365 media per its NIST 800-88 process (see Service Trust Portal). Use a certified vendor for physical media destruction. | M18: Disposition review records; Intune wipe audit log; destruction certificates; Microsoft STP data-destruction documentation. | N18: Disposition reviews need E5 Compliance / Records Management. | O18: DP-1, AM-1
A19: 3 | B19: Data Protection | C19: 3.6 | D19: Encrypt Data on End-User Devices | E19: Devices | F19: Protect | G19: ✓ | H19: ✓ | I19: ✓ | J19: Native | K19: Intune Endpoint security > Disk encryption (BitLocker, FileVault); Intune compliance policies; iOS/Android native encryption | L19: Deploy Intune BitLocker policy (XTS-AES 256, silent encryption, TPM protector, recovery keys escrowed to Entra ID) and FileVault policy for macOS (keys escrowed to Intune). Require encryption in compliance policies and enforce via Conditional Access. Mobile devices: require device encryption/passcode in compliance policy. | M19: Intune encryption report; compliance policy; Conditional Access requiring compliant device. | N19: Intune; Windows Pro+ for BitLocker. | O19: DP-5, ES-3
A20: 3 | B20: Data Protection | C20: 3.7 | D20: Establish and Maintain a Data Classification Scheme | E20: Data | F20: Govern | H20: ✓ | I20: ✓ | J20: Native | K20: Microsoft Purview Information Protection (sensitivity labels, label policies, default labels); sensitive information types; trainable classifiers | L20: Define a classification scheme (e.g. Public / Internal / Confidential / Highly Confidential) and implement it as Purview sensitivity labels with encryption, marking and container (Teams/SharePoint) settings. Publish label policies with mandatory labelling and default labels. Enable auto-labelling for SITs (client-side in E3 apps; service-side in E5). Review annually. | M20: Label taxonomy document; label & policy configuration; label usage in Activity Explorer. | N20: Manual labels in E3; auto-labelling & Activity Explorer in E5 Compliance. | O20: DP-1
A21: 3 | B21: Data Protection | C21: 3.8 | D21: Document Data Flows | E21: Data | F21: Identify | H21: ✓ | I21: ✓ | J21: Partial | K21: Purview Data Map lineage; Azure Data Factory/Fabric lineage; Visio/Whiteboard; Defender CSPM attack-path / data-sensitivity insights | L21: Document flows of sensitive data between systems, including service providers. Use Purview lineage for ADF/Synapse/Fabric pipelines and Defender CSPM data sensitivity map for cloud stores. Maintain data flow diagrams in a controlled SharePoint library and review annually or on major change. | M21: Data flow diagrams with version history; Purview lineage views. | N21: Purview Data Map consumption; Defender CSPM. | O21: DP-1, GS-3
A22: 3 | B22: Data Protection | C22: 3.9 | D22: Encrypt Data on Removable Media | E22: Data | F22: Protect | H22: ✓ | I22: ✓ | J22: Native | K22: Intune BitLocker policy (Deny write access to removable drives not protected by BitLocker / BitLocker To Go); Defender device control | L22: In Intune BitLocker settings enable 'Deny write access to removable drives not protected by BitLocker' and require BitLocker To Go with AES-256. Combine with Defender Device Control to allow only approved encrypted USB models. Apply Purview Endpoint DLP to block copying sensitive data to USB. | M22: Intune BitLocker removable drive settings; Device Control policy; Endpoint DLP rules. | N22: Windows Enterprise; MDE; Endpoint DLP needs E5 Compliance. | O22: DP-5, ES-3
A23: 3 | B23: Data Protection | C23: 3.10 | D23: Encrypt Sensitive Data in Transit | E23: Data | F23: Protect | H23: ✓ | I23: ✓ | J23: Native | K23: M365 TLS 1.2+ (default); Exchange TLS / MTA-STS / connectors with forced TLS; Azure Policy (HTTPS only, minimum TLS 1.2 on Storage, App Service, SQL); Azure VPN Gateway / ExpressRoute MACsec; Purview Message Encryption | L23: Use Azure Policy built-ins to enforce 'Secure transfer to storage accounts', 'Minimum TLS version 1.2', 'App Service should only be accessible over HTTPS' and 'Function apps HTTPS only'. Configure Exchange Online inbound/outbound connectors with mandatory TLS for partners and publish MTA-STS. Use Purview Message Encryption / sensitivity labels for sensitive email. Disable legacy protocols (SMBv1, TLS 1.0/1.1) via Intune/GPO. | M23: Azure Policy compliance report; Exchange connector config; Intune protocol hardening profiles. | N23: Azure Policy free; Purview Message Encryption in E3 (Advanced in E5). | O23: DP-3
A24: 3 | B24: Data Protection | C24: 3.11 | D24: Encrypt Sensitive Data at Rest | E24: Data | F24: Protect | H24: ✓ | I24: ✓ | J24: Native | K24: Azure Storage/SQL TDE/Disk encryption (platform, CMK via Key Vault); Azure Disk Encryption / encryption at host; M365 Customer Key; Purview sensitivity labels with encryption; Key Vault / Managed HSM | L24: Azure: platform encryption is on by default; for sensitive data use customer-managed keys in Key Vault/Managed HSM and enforce via Azure Policy (CMK, encryption at host, TDE). M365: data is encrypted at rest by default; consider Customer Key for tenant-held keys. Add application-layer encryption via sensitivity labels (Rights Management) for highly sensitive files. Protect keys with RBAC, purge protection and rotation. | M24: Azure Policy CMK compliance; Key Vault configuration; label encryption settings. | N24: Customer Key needs E5 Compliance; Key Vault/Managed HSM consumption. | O24: DP-4, DP-5, DP-6
A25: 3 | B25: Data Protection | C25: 3.12 | D25: Segment Data Processing and Storage Based on Sensitivity | E25: Network | F25: Protect | H25: ✓ | I25: ✓ | J25: Native | K25: Azure landing zones (management groups, subscriptions); VNets/NSGs/Private Endpoints; Azure Firewall; SharePoint sensitivity-labelled sites; Information Barriers; Purview Administrative Units | L25: Place sensitive workloads in dedicated subscriptions / VNets with private endpoints and no public network access (enforce with Azure Policy). Segment with NSGs and Azure Firewall. In M365, keep highly confidential data in labelled Teams/SharePoint sites with restricted membership, block guest access and use Restricted Access Control. Do not process sensitive data on assets of lower classification. | M25: Landing zone design; Azure Policy 'public network access disabled'; site/label settings. | N25: Azure Firewall/Private Link consumption; Information Barriers in E5. | O25: NS-1, NS-2, DP-1
A26: 3 | B26: Data Protection | C26: 3.13 | D26: Deploy a Data Loss Prevention Solution | E26: Data | F26: Protect | I26: ✓ | J26: Native | K26: Microsoft Purview DLP (Exchange, SharePoint, OneDrive, Teams, Endpoint, Copilot, on-prem scanner); Defender for Cloud Apps; Edge for Business DLP | L26: Deploy Purview DLP policies for each location using sensitive info types, trainable classifiers and sensitivity labels; start in simulation then enforce with block/override. Enable Endpoint DLP (USB, print, cloud upload, clipboard, unallowed apps/browsers). Use Defender for Cloud Apps session policies to control downloads from unmanaged devices. Deploy the Purview information protection scanner for on-prem file shares. Review DLP alerts in Defender XDR. | M26: DLP policy list (enforced); DLP alerts and Activity Explorer; scanner reports. | N26: Exchange/SPO/OD DLP in E3; Teams, Endpoint DLP & advanced in E5 Compliance. | O26: DP-2
A27: 3 | B27: Data Protection | C27: 3.14 | D27: Log Sensitive Data Access | E27: Data | F27: Detect | I27: ✓ | J27: Native | K27: Purview Audit (Standard/Premium), Activity Explorer; Azure Storage/SQL diagnostic logs; Sentinel; Defender for Cloud Apps | L27: Ensure Purview unified audit logging is on (default) and use Audit Premium for MailItemsAccessed and longer retention. Enable diagnostic logging for Storage (read operations), SQL auditing, Key Vault and Cosmos DB, sending to Log Analytics/Sentinel. Build Sentinel/Insider Risk alerts for mass download or access to Highly Confidential labels. | M27: Audit configuration; diagnostic setting policy compliance; sample audit search for labelled files. | N27: Audit Premium in E5; Sentinel/Log Analytics ingestion. | O27: DP-2, LT-4
A28: 4 | B28: Secure Configuration of Enterprise Assets and Software | C28: 4.1 | D28: Establish and Maintain a Secure Configuration Process | E28: Documentation | F28: Govern | G28: ✓ | H28: ✓ | I28: ✓ | J28: Native | K28: Intune security baselines & Settings catalog; Microsoft Security Compliance Toolkit; Azure Policy & Machine Configuration; Defender for Cloud secure score; Defender Vulnerability Management security baseline assessments | L28: Adopt documented baselines (e.g. CIS Benchmarks / Microsoft security baselines / OpenIntuneBaseline) for Windows, macOS, mobile, servers and M365. Deploy them through Intune security baselines/Settings catalog and, for servers, Azure Machine Configuration or GPO. Measure drift with DVM security baseline assessments (CIS/STIG profiles) and Defender for Cloud. Review annually. | M28: Baseline documents; Intune profile assignments; DVM baseline compliance %; secure score history. | N28: DVM baselines need DVM add-on / MDE P2+; Defender for Servers P2 for Machine Configuration. | O28: PV-1, PV-2, PV-3
A29: 4 | B29: Secure Configuration of Enterprise Assets and Software | C29: 4.2 | D29: Establish and Maintain a Secure Configuration Process for Network Infrastructure | E29: Network | F29: Govern | G29: ✓ | H29: ✓ | I29: ✓ | J29: Partial | K29: Azure Policy (NSG, Firewall, App Gateway, Front Door); Azure Firewall Manager policies; Defender CSPM; Network vendor tooling for physical devices | L29: Define secure configuration standards for Azure network services (Azure Policy initiatives for NSGs, WAF enabled, DDoS, no public IP on management ports) and manage Azure Firewall rules centrally via Firewall Manager. For physical switches/firewalls/Wi-Fi use vendor CIS benchmarks and config management. Review annually. | M29: Network configuration standard; Azure Policy compliance; firewall policy versions. | N29: Azure Policy free; Defender CSPM plan. | O29: NS-1, PV-1
A30: 4 | B30: Secure Configuration of Enterprise Assets and Software | C30: 4.3 | D30: Configure Automatic Session Locking on Enterprise Assets | E30: Devices | F30: Protect | G30: ✓ | H30: ✓ | I30: ✓ | J30: Native | K30: Intune Settings catalog (Interactive logon: machine inactivity limit, screen saver); macOS screen lock; mobile passcode policies; Entra Conditional Access sign-in frequency | L30: Set 'Interactive logon: Machine inactivity limit' to 900 seconds or less on Windows (15 min general purpose, 2 min mobile per CIS), macOS screensaver/password delay via Intune, and maximum inactivity before lock on iOS/Android. Use Conditional Access session controls / app idle timeout for browser sessions on unmanaged devices. | M30: Intune configuration profiles and compliance status. | N30: Intune. | O30: ES-2, PV-4
A31: 4 | B31: Secure Configuration of Enterprise Assets and Software | C31: 4.4 | D31: Implement and Manage a Firewall on Servers | E31: Devices | F31: Protect | G31: ✓ | H31: ✓ | I31: ✓ | J31: Native | K31: Windows Defender Firewall via Intune/GPO/Machine Configuration; Azure NSGs & ASGs; Azure Firewall; Defender for Cloud (JIT VM access, NSG hardening recommendations) | L31: Enable Windows Firewall on all profiles with default-deny inbound on servers (Intune/GPO/Azure Machine Configuration). Apply NSGs on every subnet/NIC with least-privilege rules; use Azure Firewall for egress. Enable Defender for Cloud Just-In-Time VM access to close management ports. Review rule sets periodically. | M31: Firewall policy; NSG rule exports; Defender for Cloud recommendation status. | N31: JIT needs Defender for Servers P2. | O31: NS-1, NS-2, ES-2
A32: 4 | B32: Secure Configuration of Enterprise Assets and Software | C32: 4.5 | D32: Implement and Manage a Firewall on End-User Devices | E32: Devices | F32: Protect | G32: ✓ | H32: ✓ | I32: ✓ | J32: Native | K32: Intune Endpoint security > Firewall (Windows), macOS firewall; Firewall rules; MDE network protection | L32: Deploy Intune Firewall policy: all profiles on, default inbound block, outbound allow, block local rule merging for public profile. Enable macOS application firewall + stealth mode. Restrict inbound rules to required management ports only. | M32: Intune firewall policy & device status report. | N32: Intune. | O32: ES-2, NS-1
A33: 4 | B33: Secure Configuration of Enterprise Assets and Software | C33: 4.6 | D33: Securely Manage Enterprise Assets and Software | E33: Devices | F33: Protect | G33: ✓ | H33: ✓ | I33: ✓ | J33: Native | K33: Intune (config-as-code via Graph); Azure Bastion; Azure Policy; Windows LAPS; Infrastructure as Code (Bicep/Terraform) in Azure DevOps/GitHub; Privileged Access Workstations | L33: Manage endpoints via Intune (version-controlled configuration, e.g. exported with IntuneManagement/Graph). Manage Azure via IaC pipelines with approvals; use secure protocols only (SSH, HTTPS, RDP via Azure Bastion). Disable insecure management protocols (Telnet, HTTP). Use Windows LAPS for local admin passwords. | M33: IaC repository with PR approvals; Bastion configuration; LAPS policy. | N33: Intune; Bastion consumption. | O33: PV-1, PA-6, NS-1
A34: 4 | B34: Secure Configuration of Enterprise Assets and Software | C34: 4.7 | D34: Manage Default Accounts on Enterprise Assets and Software | E34: Users | F34: Protect | G34: ✓ | H34: ✓ | I34: ✓ | J34: Native | K34: Windows LAPS (Intune Account protection policy); Intune 'Accounts: Rename/disable Administrator and Guest'; Azure VM admin naming policies; Entra 'break-glass' process | L34: Disable the built-in Guest account and rename/disable built-in Administrator via Intune. Use Windows LAPS (Intune) to rotate unique local admin passwords and back up to Entra ID. Change all vendor default credentials on appliances and apps. Azure: prevent default admin names (e.g. 'admin', 'administrator') via policy. | M34: Intune account protection & LAPS policy; LAPS password rotation evidence. | N34: Intune; Windows LAPS built-in. | O34: IM-3, PA-1
A35: 4 | B35: Secure Configuration of Enterprise Assets and Software | C35: 4.8 | D35: Uninstall or Disable Unnecessary Services on Enterprise Assets and Software | E35: Devices | F35: Protect | H35: ✓ | I35: ✓ | J35: Native | K35: Intune Settings catalog (System Services); Intune security baselines; Azure Machine Configuration; Defender Vulnerability Management baselines | L35: Disable unneeded Windows services (e.g. Print Spooler on servers/DCs, Xbox services, Remote Registry, SSDP) via Intune Settings catalog or GPO. Remove optional features (SMBv1, PowerShell v2, Telnet client). Measure with DVM security baseline assessment and Defender for Cloud OS configuration recommendations. | M35: Intune service-config profile; DVM baseline report. | N35: Intune; DVM add-on. | O35: PV-1, ES-2
A36: 4 | B36: Secure Configuration of Enterprise Assets and Software | C36: 4.9 | D36: Configure Trusted DNS Servers on Enterprise Assets | E36: Devices | F36: Protect | H36: ✓ | I36: ✓ | J36: Native | K36: Intune (DNS settings / DoH via Settings catalog); Azure DNS / Azure DNS Private Resolver; Azure Firewall DNS proxy; Microsoft Entra Internet Access | L36: Configure endpoints to use enterprise-controlled DNS (on-prem AD DNS, Azure DNS Private Resolver, or a protective DNS service) and enforce DoH templates via Intune. In Azure, point VNets to Azure Firewall DNS proxy / Private Resolver. Block outbound DNS (UDP/TCP 53, DoH endpoints) to anything else at the firewall. | M36: Intune DNS/DoH profile; VNet DNS settings; firewall rule blocking external DNS. | N36: Azure Firewall/Private Resolver consumption; Entra Internet Access licence. | O36: NS-10
A37: 4 | B37: Secure Configuration of Enterprise Assets and Software | C37: 4.10 | D37: Enforce Automatic Device Lockout on Portable End-User Devices | E37: Devices | F37: Protect | H37: ✓ | I37: ✓ | J37: Native | K37: Intune device restrictions / compliance (max failed sign-ins before wipe); Windows 'Interactive logon: Machine account lockout threshold' with BitLocker; iOS/Android passcode policies | L37: Set maximum failed unlock attempts before wipe (≤10 for phones/tablets, ≤20 for laptops per CIS) using Intune iOS/Android device restrictions and Windows 'Machine account lockout threshold' (requires BitLocker). Enforce through compliance policies. | M37: Intune device restriction profiles. | N37: Intune. | O37: ES-2
A38: 4 | B38: Secure Configuration of Enterprise Assets and Software | C38: 4.11 | D38: Enforce Remote Wipe Capability on Portable End-User Devices | E38: Devices | F38: Protect | H38: ✓ | I38: ✓ | J38: Native | K38: Intune remote actions (Wipe, Retire, Selective wipe of app data via App Protection Policies) | L38: Enrol all portable devices in Intune (or use MAM App Protection Policies for BYOD) so Wipe / Retire / selective wipe can be issued when a device is lost or an employee leaves. Document the lost-device procedure and link it to incident reporting (17.3). | M38: Intune enrolment coverage; remote wipe action log; lost-device procedure. | N38: Intune. | O38: ES-3, AM-1
A39: 4 | B39: Secure Configuration of Enterprise Assets and Software | C39: 4.12 | D39: Separate Enterprise Workspaces on Mobile End-User Devices | E39: Devices | F39: Protect | I39: ✓ | J39: Native | K39: Intune Android Enterprise Work Profile; iOS User Enrollment / managed apps; Intune App Protection Policies (MAM); Windows MAM for Edge | L39: Use Android Enterprise personally-owned work profile and iOS/iPadOS account-driven User Enrollment for BYOD. Apply App Protection Policies to restrict copy/paste and save-as between managed and unmanaged apps, require PIN, encrypt app data. Require approved client apps / app protection via Conditional Access. | M39: Enrolment profiles; App Protection Policy settings; Conditional Access 'require app protection policy'. | N39: Intune; Entra ID P1. | O39: ES-3, DP-2
A40: 5 | B40: Account Management | C40: 5.1 | D40: Establish and Maintain an Inventory of Accounts | E40: Users | F40: Identify | G40: ✓ | H40: ✓ | I40: ✓ | J40: Native | K40: Microsoft Entra ID (users, guests, workload identities); Active Directory; Defender for Identity; Entra ID Governance (lifecycle workflows); Graph API exports | L40: Treat Entra ID (synced from AD/HR) as the account inventory: name, UPN, department, manager, start/end date via HR-driven provisioning (Workday/SuccessFactors) or Entra Connect. Export users, guests and admins quarterly via Graph and validate that all active accounts are authorized. Include local and application accounts not in Entra. | M40: Quarterly account inventory export & validation sign-off. | N40: Entra ID Free/P1; HR provisioning & lifecycle workflows need Entra ID Governance. | O40: IM-1, PA-1
A41: 5 | B41: Account Management | C41: 5.2 | D41: Use Unique Passwords | E41: Users | F41: Protect | G41: ✓ | H41: ✓ | I41: ✓ | J41: Native | K41: Entra Password Protection (global + custom banned lists, on-prem agent); Windows Hello for Business / passkeys (passwordless); Windows LAPS; Entra ID MFA | L41: Enable Entra Password Protection for cloud and on-prem AD (deploy DC agent) with a custom banned-password list. Prefer passwordless (Windows Hello for Business, FIDO2/passkeys via Authentication Methods policy). Where passwords remain, require 14+ characters (or 8+ with MFA) per CIS. Use LAPS for local admin uniqueness. | M41: Password Protection config; Authentication methods policy; registration report. | N41: Password Protection for on-prem AD requires Entra ID P1. | O41: IM-6, IM-8
A42: 5 | B42: Account Management | C42: 5.3 | D42: Disable Dormant Accounts | E42: Users | F42: Protect | G42: ✓ | H42: ✓ | I42: ✓ | J42: Native | K42: Entra ID Governance access reviews (inactive users); signInActivity via Graph; Entra lifecycle workflows; Defender for Identity (stale accounts); Entra guest inactive reviews | L42: Configure access reviews for inactive users (no sign-in in 45 days) with auto-disable, including guests. Use a scheduled Graph/Logic App/Azure Automation runbook on signInActivity to disable accounts dormant ≥45 days. Defender for Identity/Secure Score 'Remove dormant accounts from sensitive groups' covers AD. | M42: Access review history; automation runbook and logs; disabled-account report. | N42: Inactive-user access reviews need Entra ID P2 / Governance. | O42: IM-1, PA-4
A43: 5 | B43: Account Management | C43: 5.4 | D43: Restrict Administrator Privileges to Dedicated Administrator Accounts | E43: Users | F43: Protect | G43: ✓ | H43: ✓ | I43: ✓ | J43: Native | K43: Entra separate cloud-only admin accounts; Privileged Identity Management; Intune Endpoint Privilege Management; Windows LAPS; Conditional Access for admins | L43: Create dedicated cloud-only admin accounts (not synced, no mailbox) for all privileged roles; daily-driver accounts hold no admin rights. Make Entra and Azure roles eligible-only through PIM. Remove users from local Administrators using Intune Account protection (Local user group membership) and use Endpoint Privilege Management for elevation needs. | M43: Admin account list; PIM eligible assignments; Intune local group policy. | N43: PIM needs Entra ID P2; EPM needs Intune Suite. | O43: PA-1, PA-2
A44: 5 | B44: Account Management | C44: 5.5 | D44: Establish and Maintain an Inventory of Service Accounts | E44: Users | F44: Identify | H44: ✓ | I44: ✓ | J44: Native | K44: Entra workload identities (service principals, managed identities); Microsoft Entra Workload ID; Defender for Identity (service account discovery); AD gMSA; Defender for Cloud Apps app governance | L44: Inventory all service principals/app registrations, managed identities and AD service accounts with owner, purpose and review date. Prefer managed identities and gMSA over passwords/secrets. Use Defender for Identity service account page and Workload ID access reviews; review quarterly. | M44: Service account register; app registration export with owners; quarterly review evidence. | N44: Workload ID Premium for workload access reviews / CA; MDI in E5 Security. | O44: IM-3, PA-1
A45: 5 | B45: Account Management | C45: 5.6 | D45: Centralize Account Management | E45: Users | F45: Govern | H45: ✓ | I45: ✓ | J45: Native | K45: Microsoft Entra ID (single identity plane); Entra Connect / Cloud Sync; SCIM provisioning to SaaS; Entra ID Governance | L45: Make Entra ID the central directory: sync AD via Entra Connect / Cloud Sync, federate SaaS apps via SAML/OIDC with SCIM provisioning, and avoid local app accounts. Use HR-driven provisioning and lifecycle workflows for joiner/mover/leaver. | M45: Enterprise apps with SSO + provisioning; identity architecture diagram. | N45: Entra ID P1; Governance for lifecycle workflows. | O45: IM-1
A46: 6 | B46: Access Control Management | C46: 6.1 | D46: Establish an Access Granting Process | E46: Users | F46: Govern | G46: ✓ | H46: ✓ | I46: ✓ | J46: Native | K46: Entra ID Governance Entitlement Management (access packages with approval); ServiceNow/ITSM integration; Lifecycle workflows | L46: Document the access-granting process and implement it through Entra access packages: requestable bundles of groups/apps/SharePoint sites with manager + resource-owner approval, expiry and justification. Automate joiner access via HR-driven provisioning and lifecycle workflows. | M46: Access-granting procedure; access package catalogue; approval history. | N46: Entitlement Management needs Entra ID P2 / Governance. | O46: IM-1, PA-7
A47: 6 | B47: Access Control Management | C47: 6.2 | D47: Establish an Access Revoking Process | E47: Users | F47: Govern | G47: ✓ | H47: ✓ | I47: ✓ | J47: Native | K47: Entra lifecycle workflows (leaver tasks); HR inbound provisioning; access package expiry; Revoke sessions (Graph revokeSignInSessions); Intune retire/wipe | L47: Trigger leaver workflow from HR end date: disable account, remove group/licence assignments, revoke refresh tokens, remove from access packages, retire devices, convert mailbox. Mover workflows remove previous role access. Measure time-to-revoke against your SLA. | M47: Leaver workflow history; audit log showing disable + revoke within SLA. | N47: Lifecycle workflows need Entra ID Governance. | O47: IM-1, PA-4
A48: 6 | B48: Access Control Management | C48: 6.3 | D48: Require MFA for Externally-Exposed Applications | E48: Users | F48: Protect | G48: ✓ | H48: ✓ | I48: ✓ | J48: Native | K48: Entra Conditional Access (require MFA / authentication strength); Entra Application Proxy / Private Access; SSO for SaaS | L48: Conditional Access policy: All users, All resources, require MFA (phishing-resistant authentication strength preferred), excluding only break-glass accounts. Block legacy authentication. Publish on-prem web apps via Entra Application Proxy/Private Access so they inherit CA; federate third-party SaaS through Entra for MFA. | M48: CA policy export; sign-in logs showing MFA; legacy auth blocked report. | N48: Entra ID P1 (Security Defaults as free alternative). | O48: IM-6, IM-7
A49: 6 | B49: Access Control Management | C49: 6.4 | D49: Require MFA for Remote Network Access | E49: Users | F49: Protect | G49: ✓ | H49: ✓ | I49: ✓ | J49: Native | K49: Microsoft Entra Private Access (Global Secure Access); Azure VPN Gateway with Entra ID authentication + CA; NPS extension for Entra MFA (RADIUS VPNs); Azure Bastion with CA | L49: Replace legacy VPN with Entra Private Access, or configure Azure VPN Gateway P2S with Entra ID authentication. For third-party VPNs use SAML to Entra or the NPS extension for MFA. Apply Conditional Access requiring MFA + compliant device for the VPN/Private Access apps. | M49: VPN/GSA app CA policy; sign-in logs for VPN app. | N49: Entra ID P1; Entra Private Access licence (Suite). | O49: IM-7, NS-1
A50: 6 | B50: Access Control Management | C50: 6.5 | D50: Require MFA for Administrative Access | E50: Users | F50: Protect | G50: ✓ | H50: ✓ | I50: ✓ | J50: Native | K50: Conditional Access (directory roles, Azure management) with phishing-resistant authentication strength; PIM activation MFA; Azure mandatory MFA; Defender for Identity | L50: CA policy targeting all privileged directory roles requiring phishing-resistant MFA (FIDO2, WHfB, certificate). CA policy for 'Windows Azure Service Management API'/Azure management requiring MFA for all users. Require MFA on PIM activation. Third-party admin consoles federated through Entra. | M50: CA policies; authentication strength config; PIM role settings. | N50: Entra ID P1 (P2 for PIM). | O50: PA-1, IM-6
A51: 6 | B51: Access Control Management | C51: 6.6 | D51: Establish and Maintain an Inventory of Authentication and Authorization Systems | E51: Software | F51: Identify | H51: ✓ | I51: ✓ | J51: Partial | K51: Entra ID enterprise applications / app registrations; Defender for Cloud Apps (discovered apps & OAuth apps); AD/ADFS; Defender for Identity | L51: Document every authentication/authorization system: Entra ID, AD DS, ADFS, PKI, RADIUS/NPS, app-local auth, SaaS IdPs. Use Entra enterprise app list and Defender for Cloud Apps app governance to find apps using non-Entra auth and migrate them. Review annually. | M51: Auth systems inventory; enterprise apps export. | N51: Defender for Cloud Apps / app governance in E5. | O51: IM-1, IM-2
A52: 6 | B52: Access Control Management | C52: 6.7 | D52: Centralize Access Control | E52: Users | F52: Protect | H52: ✓ | I52: ✓ | J52: Native | K52: Entra ID SSO (SAML/OIDC/password-based) for SaaS & on-prem apps; Entra Application Proxy / Private Access; ADFS→Entra migration; Conditional Access | L52: Federate all SaaS and custom apps to Entra ID and apply Conditional Access centrally. Migrate ADFS relying parties to Entra. Publish on-prem apps via Application Proxy or Private Access. Use Azure RBAC with Entra groups for cloud resources. | M52: Enterprise apps with SSO configured; % apps federated. | N52: Entra ID P1. | O52: IM-1, IM-4
A53: 6 | B53: Access Control Management | C53: 6.8 | D53: Define and Maintain Role-Based Access Control | E53: Data | F53: Govern | I53: ✓ | J53: Native | K53: Entra ID roles & custom roles; Azure RBAC & custom roles; PIM for groups; Entra Administrative Units; Exchange/Intune/Defender RBAC (unified RBAC); access reviews | L53: Define job roles and the minimal rights each needs; implement as role-assignable groups / access packages mapped to Entra, Azure, Intune and Defender XDR unified RBAC roles. Scope with Administrative Units and management groups. Run access reviews on role assignments at least annually and on PIM groups. | M53: RBAC role matrix; role assignment export; access review results. | N53: Entra ID P2 / Governance for PIM & reviews. | O53: PA-7, PA-3
A54: 7 | B54: Continuous Vulnerability Management | C54: 7.1 | D54: Establish and Maintain a Vulnerability Management Process | E54: Documentation | F54: Govern | G54: ✓ | H54: ✓ | I54: ✓ | J54: Process | K54: Defender Vulnerability Management; Defender for Cloud; Microsoft Security Exposure Management | L54: Document the vulnerability management process: scope, scanning frequency, risk rating (CVSS/EPSS/exposure score), SLAs per severity, exceptions. Implement with DVM (endpoints/servers), Defender for Cloud (cloud workloads, containers, IaC) and Exposure Management for prioritisation. Review annually. | M54: Approved VM process; SLA definitions; exception register. | N54: DVM add-on / Defender for Servers P2. | O54: PV-5, GS-1
A55: 7 | B55: Continuous Vulnerability Management | C55: 7.2 | D55: Establish and Maintain a Remediation Process | E55: Documentation | F55: Govern | G55: ✓ | H55: ✓ | I55: ✓ | J55: Native | K55: DVM remediation requests (Intune integration); Defender for Cloud governance rules (owners & due dates); Intune; Azure Update Manager | L55: Define risk-based remediation timelines and owners. Use DVM 'Request remediation' integrated with Intune tasks and Defender for Cloud governance rules to assign owners and due dates automatically; track overdue items monthly. | M55: Remediation process; governance rule configuration; overdue remediation report. | N55: DVM / Defender CSPM for governance rules. | O55: PV-6
A56: 7 | B56: Continuous Vulnerability Management | C56: 7.3 | D56: Perform Automated Operating System Patch Management | E56: Software | F56: Protect | G56: ✓ | H56: ✓ | I56: ✓ | J56: Native | K56: Windows Autopatch / Windows Update for Business rings (Intune); Hotpatch; Azure Update Manager (Azure + Arc servers); Intune iOS/macOS/Android update policies | L56: Use Windows Autopatch or Intune update rings with deadlines (quality updates within 7 days, feature updates on schedule). Enable hotpatch where supported. Patch Azure and Arc-enabled servers with Azure Update Manager maintenance configurations (at least monthly). Enforce macOS/iOS updates via Intune DDM update policies. | M56: Autopatch/update ring reports; Update Manager compliance; OS version compliance policy. | N56: Autopatch in E3/E5; Update Manager free for Azure VMs, charged for Arc (unless Defender for Servers P2). | O56: PV-7
A57: 7 | B57: Continuous Vulnerability Management | C57: 7.4 | D57: Perform Automated Application Patch Management | E57: Software | F57: Protect | G57: ✓ | H57: ✓ | I57: ✓ | J57: Partial | K57: M365 Apps update channels (Intune/Cloud Update); Edge update policies; Intune Enterprise App Management (Intune Suite); Windows Package Manager; DVM recommendations | L57: Configure M365 Apps on Monthly Enterprise/Current channel via Cloud Update, Edge auto-update via Intune. Use Intune Enterprise App Catalog (auto-update of third-party apps) or WinGet / third-party patching (e.g. Patch My PC) for other apps. Track residual risk in DVM. | M57: Update channel config; Enterprise App Management update reports; DVM weaknesses trend. | N57: Enterprise App Management needs Intune Suite/add-on. | O57: PV-7
A58: 7 | B58: Continuous Vulnerability Management | C58: 7.5 | D58: Perform Automated Vulnerability Scans of Internal Enterprise Assets | E58: Software | F58: Identify | H58: ✓ | I58: ✓ | J58: Native | K58: Defender Vulnerability Management (agent-based, continuous); Defender for Servers (MDE or agentless scanning); Defender for Containers; Defender for SQL vulnerability assessment; authenticated network device scans (DVM) | L58: Rely on continuous agent-based assessment via MDE on all endpoints/servers, plus agentless machine scanning in Defender for Cloud. Enable DVM authenticated scans for network devices and Windows assets without the agent. Enable SQL vulnerability assessment and container registry scanning. Results at least quarterly (continuous in practice). | M58: DVM exposure score; Defender for Cloud vulnerability recommendations; scan coverage. | N58: MDE P2/DVM; Defender for Servers P2, Containers, SQL plans. | O58: PV-5
A59: 7 | B59: Continuous Vulnerability Management | C59: 7.6 | D59: Perform Automated Vulnerability Scans of Externally-Exposed Enterprise Assets | E59: Software | F59: Identify | H59: ✓ | I59: ✓ | J59: Native | K59: Defender External Attack Surface Management (EASM); Defender for Cloud (internet-exposure insights); Exposure Management | L59: Discover external assets with Defender EASM (domains, IPs, hosts, certs) and review CVEs/misconfigurations on internet-facing services at least monthly. Use Defender CSPM attack paths for exposed VMs. Consider a SCAN-certified external scanner if a regulatory requirement (e.g. PCI ASV) applies. | M59: EASM inventory & findings dashboard; monthly review records. | N59: Defender EASM consumption-based. | O59: PV-5, NS-1
A60: 7 | B60: Continuous Vulnerability Management | C60: 7.7 | D60: Remediate Detected Vulnerabilities | E60: Software | F60: Respond | H60: ✓ | I60: ✓ | J60: Native | K60: DVM remediation; Intune; Azure Update Manager; Defender for Cloud recommendations & 'Fix' / Azure Policy remediation | L60: Remediate per process (7.2) using Intune/Update Manager deployments, Defender for Cloud quick-fix and Azure Policy remediation tasks. Validate closure through the next DVM assessment; report monthly against SLA. | M60: Monthly remediation SLA report; DVM trend. | N60: As 7.2/7.5. | O60: PV-6
A61: 8 | B61: Audit Log Management | C61: 8.1 | D61: Establish and Maintain an Audit Log Management Process | E61: Documentation | F61: Govern | G61: ✓ | H61: ✓ | I61: ✓ | J61: Process | K61: Microsoft Sentinel; Log Analytics; Purview Audit; Azure Monitor diagnostic settings; Defender XDR | L61: Document what is logged (identity, endpoint, cloud control plane, data access, network), where it is stored, retention, review frequency and responsibilities. Map log sources to Sentinel data connectors. Review annually. | M61: Audit log policy; log source matrix. | N61: — | O61: LT-1, LT-6
A62: 8 | B62: Audit Log Management | C62: 8.2 | D62: Collect Audit Logs | E62: Data | F62: Detect | G62: ✓ | H62: ✓ | I62: ✓ | J62: Native | K62: Purview unified audit log; Entra sign-in & audit logs; Azure Activity Log; Defender XDR; Windows event logs via Azure Monitor Agent; Azure Policy 'Deploy diagnostic settings' | L62: Confirm Purview audit is on. Export Entra sign-in/audit logs and Azure Activity Logs to Log Analytics/Sentinel. Use Azure Policy initiatives to deploy diagnostic settings for all resource types. Enable Windows advanced audit policy via Intune and collect with AMA. Onboard MDE so endpoint telemetry is recorded. | M62: Diagnostic settings policy compliance; Sentinel data connector status. | N62: Entra log export needs P1; Sentinel/LA ingestion. | O62: LT-3, LT-4
A63: 8 | B63: Audit Log Management | C63: 8.3 | D63: Ensure Adequate Audit Log Storage | E63: Data | F63: Protect | G63: ✓ | H63: ✓ | I63: ✓ | J63: Native | K63: Log Analytics workspaces (retention, long-term/archive tier, data lake); Sentinel data lake; Azure Storage (immutable) | L63: Size Log Analytics/Sentinel workspaces and set retention per policy; use auxiliary/basic logs or Sentinel data lake for high-volume sources. Configure daily cap alerts (not hard caps for security data). Archive to immutable Storage for long retention. | M63: Workspace retention settings; ingestion/capacity monitoring alerts. | N63: Ingestion and retention costs. | O63: LT-6
A64: 8 | B64: Audit Log Management | C64: 8.4 | D64: Standardize Time Synchronization | E64: Network | F64: Protect | H64: ✓ | I64: ✓ | J64: Native | K64: Windows Time service (AD domain hierarchy); Intune Settings catalog NTP; Azure VMs host time sync / time.windows.com | L64: Configure the AD PDC emulator to sync to at least two reliable NTP sources; domain members sync via domain hierarchy. For Entra-joined devices set NTP servers through Intune (Settings catalog: Time Providers). Azure VMs use host time sync. Monitor time skew. | M64: PDC NTP configuration; Intune profile; w32tm status samples. | N64: — | O64: LT-7
A65: 8 | B65: Audit Log Management | C65: 8.5 | D65: Collect Detailed Audit Logs | E65: Data | F65: Detect | H65: ✓ | I65: ✓ | J65: Native | K65: Windows advanced audit policies (Intune Settings catalog / security baseline); MDE telemetry; Sysmon; Purview Audit Premium; Azure resource logs | L65: Enable advanced audit subcategories (logon, process creation, account management, policy change, object access for sensitive shares) per CIS/Microsoft baselines. MDE provides process, network, file and registry telemetry (30 days in Advanced Hunting, longer via streaming to Sentinel). Include event source, date, user, timestamp, source/destination addresses. | M65: Audit policy configuration; sample events in Sentinel. | N65: MDE P2; Audit Premium in E5. | O65: LT-3, LT-4
A66: 8 | B66: Audit Log Management | C66: 8.6 | D66: Collect DNS Query Audit Logs | E66: Data | F66: Detect | H66: ✓ | I66: ✓ | J66: Native | K66: Windows DNS Server analytical logs via AMA (Sentinel 'Windows DNS Events via AMA' connector); Azure DNS Private Resolver / Azure Firewall DNS proxy logs; MDE DnsEvents/DeviceNetworkEvents; Entra Internet Access logs | L66: Enable DNS analytic logging on Windows DNS servers and ingest with the Sentinel DNS AMA connector. Enable Azure Firewall DNS proxy logs / DNS security policy logs for VNets. Use Sentinel ASIM DNS parsers and threat-intel matching analytics. | M66: Sentinel DNS connector status; sample DNS query logs. | N66: Sentinel ingestion. | O66: LT-4, NS-10
A67: 8 | B67: Audit Log Management | C67: 8.7 | D67: Collect URL Request Audit Logs | E67: Data | F67: Detect | H67: ✓ | I67: ✓ | J67: Native | K67: Defender for Endpoint network protection & web content filtering (DeviceNetworkEvents); Defender for Cloud Apps; Entra Internet Access traffic logs; Azure Firewall application rule logs; Defender for Office 365 Safe Links click logs | L67: Enable MDE network protection (block mode) and web content filtering so URL requests are logged per device. Route Internet traffic through Entra Internet Access or Azure Firewall Premium for proxy-style URL logs. Ingest into Sentinel. | M67: Network protection policy; web activity reports; firewall application logs. | N67: MDE P2; Entra Internet Access; Azure Firewall Premium. | O67: LT-3, NS-8
A68: 8 | B68: Audit Log Management | C68: 8.8 | D68: Collect Command-Line Audit Logs | E68: Data | F68: Detect | H68: ✓ | I68: ✓ | J68: Native | K68: Defender for Endpoint (process command lines); Intune: 'Include command line in process creation events' + PowerShell script block & module logging; Azure Monitor Agent | L68: Enable process creation auditing with command line (Event 4688), PowerShell script block logging and module logging via Intune. MDE captures command lines in DeviceProcessEvents. Collect Linux auditd/bash history via AMA/MDE for Linux. Ingest to Sentinel. | M68: Intune profile; DeviceProcessEvents samples; PowerShell 4104 events. | N68: MDE P2. | O68: LT-3
A69: 8 | B69: Audit Log Management | C69: 8.9 | D69: Centralize Audit Logs | E69: Data | F69: Detect | H69: ✓ | I69: ✓ | J69: Native | K69: Microsoft Sentinel (in Defender portal); Log Analytics; Defender XDR streaming API; Azure Monitor Agent; syslog/CEF via AMA | L69: Deploy Sentinel as the central SIEM; connect Microsoft sources (Defender XDR, Entra, Azure Activity, Office 365, Purview) and third-party sources (firewalls, VPN, Linux) via AMA/CEF/Codeless connectors. Use one or few workspaces per region/regulation. | M69: Sentinel data connector list; source coverage matrix vs 8.1. | N69: Sentinel consumption; some M365 data free in Sentinel. | O69: LT-5
A70: 8 | B70: Audit Log Management | C70: 8.10 | D70: Retain Audit Logs | E70: Data | F70: Protect | H70: ✓ | I70: ✓ | J70: Native | K70: Log Analytics retention (interactive + long-term); Sentinel data lake; Purview Audit retention policies (Audit Premium 1-10 years); immutable Blob storage | L70: Retain audit logs at least 90 days (CIS minimum); set Purview audit retention policies (180 days default for Audit Standard, 1 year+ for Premium). Configure workspace total retention to meet legal/regulatory needs (often 1-7 years). | M70: Workspace retention config; Purview audit retention policies. | N70: Audit Premium (E5) for 1yr+/10yr retention add-on. | O70: LT-6
A71: 8 | B71: Audit Log Management | C71: 8.11 | D71: Conduct Audit Log Reviews | E71: Data | F71: Detect | H71: ✓ | I71: ✓ | J71: Native | K71: Sentinel analytics rules, workbooks, UEBA, hunting queries; Defender XDR incidents; Security Copilot | L71: Enable Sentinel analytics (Microsoft content hub solutions, Fusion/multistage attack detection), UEBA and anomaly rules. Weekly (or more frequent) review of workbooks and hunting queries; document reviews and findings. | M71: Analytics rule list; weekly review log / hunting notebook. | N71: Sentinel; Security Copilot optional (SCU). | O71: LT-1, LT-2
A72: 8 | B72: Audit Log Management | C72: 8.12 | D72: Collect Service Provider Logs | E72: Data | F72: Detect | I72: ✓ | J72: Native | K72: Sentinel connectors for SaaS (Defender for Cloud Apps app connectors, Okta, AWS CloudTrail, GCP, Salesforce, ServiceNow etc.); Codeless Connector Framework; Azure Lighthouse logs | L72: Where supported, collect logs from service providers (other clouds, SaaS, MSP activity via Lighthouse/GDAP audit). Use Defender for Cloud Apps API connectors and Sentinel connectors. Include log access in contracts (15.4) where not technically available. | M72: Connector list; SaaS log samples; contract clauses. | N72: Sentinel; Defender for Cloud Apps (E5). | O72: LT-1, LT-4
A73: 9 | B73: Email and Web Browser Protections | C73: 9.1 | D73: Ensure Use of Only Fully Supported Browsers and Email Clients | E73: Software | F73: Protect | G73: ✓ | H73: ✓ | I73: ✓ | J73: Native | K73: Microsoft Edge (Intune policies, auto-update); Outlook (M365 Apps current channel); Intune compliance/ASR; App Control to block unsupported browsers; Conditional Access client app restrictions | L73: Standardise on Edge (and/or a managed Chrome) with auto-update via Intune; remove/block IE mode where not needed. Keep Outlook on supported M365 Apps channels; block legacy clients (Basic auth already retired) and use CA 'Require approved client app' on mobile. Use DVM to find out-of-support browser versions. | M73: Intune browser policy; DVM browser version report; CA policy. | N73: Intune; Entra ID P1. | O73: ES-2, PV-6
A74: 9 | B74: Email and Web Browser Protections | C74: 9.2 | D74: Use DNS Filtering Services | E74: Network | F74: Protect | G74: ✓ | H74: ✓ | I74: ✓ | J74: Native | K74: Defender for Endpoint network protection (blocks malicious domains incl. DNS-based); Microsoft Entra Internet Access (web/DNS filtering); Azure Firewall threat intel (DNS proxy); Azure DNS security policy (DNS threat intelligence) | L74: Enable MDE network protection in block mode on all devices (works on/off network). For servers/VNets, use Azure DNS security policies / Azure Firewall threat-intel deny with DNS proxy. Optionally use Entra Internet Access or a protective DNS service for resolution-level blocking. | M74: Network protection policy; DNS security policy; block events. | N74: MDE P1/P2; Entra Internet Access; Azure Firewall/DNS policy consumption. | O74: NS-10, ES-1
A75: 9 | B75: Email and Web Browser Protections | C75: 9.3 | D75: Maintain and Enforce Network-Based URL Filters | E75: Network | F75: Protect | H75: ✓ | I75: ✓ | J75: Native | K75: MDE web content filtering & custom URL indicators; Entra Internet Access web content filtering; Azure Firewall Premium URL/web categories; Defender for Cloud Apps unsanctioned app blocking | L75: Define categories to block (malicious, adult, gambling, uncategorized, etc.) in MDE web content filtering and/or Entra Internet Access. Add custom URL/domain indicators. For Azure egress use Azure Firewall Premium web categories and TLS inspection. Block unsanctioned SaaS via MDCA + MDE. | M75: WCF policy; Entra IA filtering profile; firewall policy. | N75: MDE P2 (WCF); Entra Internet Access; Azure Firewall Premium. | O75: NS-8
A76: 9 | B76: Email and Web Browser Protections | C76: 9.4 | D76: Restrict Unnecessary or Unauthorized Browser and Email Client Extensions | E76: Software | F76: Protect | H76: ✓ | I76: ✓ | J76: Native | K76: Intune Edge/Chrome policies (ExtensionInstallBlocklist / Allowlist / ExtensionSettings); Outlook add-in management (M365 admin center Integrated Apps, user consent to add-ins off); DVM browser extension inventory | L76: Block all browser extensions by default ('*' in blocklist) and allow approved ones via Intune. Disable user-installed Outlook add-ins (Exchange user role assignment policy) and deploy approved add-ins centrally. Review DVM browser extension inventory for risky permissions. | M76: Intune browser extension policies; Exchange role policy; extension inventory. | N76: Intune; DVM add-on for extensions inventory. | O76: ES-2, AM-5
A77: 9 | B77: Email and Web Browser Protections | C77: 9.5 | D77: Implement DMARC | E77: Network | F77: Protect | H77: ✓ | I77: ✓ | J77: Native | K77: Exchange Online SPF, DKIM signing, DMARC (DNS); Defender for Office 365 anti-spoofing; DMARC reporting | L77: Publish SPF (-all) for all sending domains including non-sending/parked domains (v=spf1 -all). Enable DKIM signing in Defender portal for every accepted domain. Publish DMARC starting p=none with rua reporting, move to quarantine then p=reject. Set inbound honour-DMARC policy in anti-phishing. | M77: DNS records; DKIM status; DMARC aggregate reports. | N77: EOP (included). | O77: NS-8
A78: 9 | B78: Email and Web Browser Protections | C78: 9.6 | D78: Block Unnecessary File Types | E78: Network | F78: Protect | H78: ✓ | I78: ✓ | J78: Native | K78: Exchange Online Protection anti-malware common attachment filter; Defender for Office 365 Safe Attachments; Exchange mail flow rules; SharePoint blocked file types; MDE ASR rules | L78: Enable the common attachment filter with an extended blocked-extension list (e.g. .exe, .js, .vbs, .iso, .img, .lnk, .hta, .one where not needed). Use mail flow rules for archives containing executables. Block file types in SharePoint/OneDrive sync where appropriate. ASR rule 'Block executable content from email client and webmail'. | M78: Anti-malware policy file type list; mail flow rules; ASR report. | N78: EOP; Defender for Office 365 P1/P2. | O78: NS-8, ES-1
A79: 9 | B79: Email and Web Browser Protections | C79: 9.7 | D79: Deploy and Maintain Email Server Anti-Malware Protections | E79: Network | F79: Protect | I79: ✓ | J79: Native | K79: Exchange Online Protection; Defender for Office 365 (Safe Attachments, Safe Links, Zero-hour auto purge, anti-phishing, preset Strict/Standard policies); Exchange Server AMSI integration | L79: Apply Defender for Office 365 Standard/Strict preset security policies to all users. Enable Safe Attachments (Dynamic Delivery/Block) for email, SharePoint, OneDrive and Teams; Safe Links with click-time protection; ZAP. On-prem Exchange: enable AMSI integration and MDE on Exchange servers. | M79: Preset policy assignments; configuration analyzer results; threat protection status report. | N79: Defender for Office 365 P1 (P2 in E5). | O79: ES-1, NS-8
A80: 10 | B80: Malware Defenses | C80: 10.1 | D80: Deploy and Maintain Anti-Malware Software | E80: Devices | F80: Protect | G80: ✓ | H80: ✓ | I80: ✓ | J80: Native | K80: Microsoft Defender Antivirus + Defender for Endpoint (Windows, macOS, Linux, iOS, Android); Defender for Servers; Intune Antivirus policy | L80: Deploy Defender Antivirus in active mode with MDE across all OS platforms via Intune / Defender for Servers auto-provisioning. Enable real-time, cloud-delivered protection (High), block at first sight, PUA blocking and tamper protection. Monitor health in Defender portal. | M80: Intune antivirus report; MDE device health; tamper protection status. | N80: MDE P1/P2; Defender for Servers P1/P2. | O80: ES-1, ES-2
A81: 10 | B81: Malware Defenses | C81: 10.2 | D81: Configure Automatic Anti-Malware Signature Updates | E81: Devices | F81: Protect | G81: ✓ | H81: ✓ | I81: ✓ | J81: Native | K81: Defender Antivirus security intelligence updates (Windows Update / MMPC); Intune update controls; gradual release channels | L81: Configure security intelligence update checks every ≤4 hours (default ~hourly via cloud), engine/platform updates via Intune 'Defender update controls' channels. Alert on devices with signatures older than 3 days. | M81: Antivirus report showing signature currency. | N81: MDE. | O81: ES-3
A82: 10 | B82: Malware Defenses | C82: 10.3 | D82: Disable Autorun and Autoplay for Removable Media | E82: Devices | F82: Protect | G82: ✓ | H82: ✓ | I82: ✓ | J82: Native | K82: Intune Settings catalog (Turn off Autoplay, Disallow Autoplay for non-volume devices, default AutoRun behaviour); ASR rule 'Block untrusted and unsigned processes that run from USB' | L82: Configure 'Turn off Autoplay: All drives', 'Set default behavior for AutoRun: Do not execute any autorun commands', and 'Disallow Autoplay for non-volume devices' via Intune. Enable the USB ASR rule in block mode. | M82: Intune configuration profile; ASR report. | N82: Intune; MDE. | O82: ES-2
A83: 10 | B83: Malware Defenses | C83: 10.4 | D83: Configure Automatic Anti-Malware Scanning of Removable Media | E83: Devices | F83: Detect | H83: ✓ | I83: ✓ | J83: Native | K83: Defender Antivirus 'Scan removable drives' (full scan) + real-time protection; Device Control | L83: Enable 'Allow scanning of removable drives' (AllowFullScanRemovableDriveScanning) via Intune Antivirus policy; real-time protection scans on access. Use Device Control to restrict unknown removable media. | M83: Intune antivirus policy setting. | N83: MDE. | O83: ES-1
A84: 10 | B84: Malware Defenses | C84: 10.5 | D84: Enable Anti-Exploitation Features | E84: Devices | F84: Protect | H84: ✓ | I84: ✓ | J84: Native | K84: Defender Exploit Protection (system & app mitigations: DEP, ASLR, CFG); Attack Surface Reduction rules; Credential Guard / LSA protection / VBS / HVCI; Microsoft Vulnerable Driver Blocklist; Smart App Control; macOS Gatekeeper/SIP | L84: Deploy Exploit Protection XML baseline and ASR rules (block mode) via Intune Endpoint security. Enable VBS, memory integrity (HVCI), Credential Guard, LSA protection and the vulnerable driver blocklist. Keep Gatekeeper and SIP enabled on macOS. | M84: ASR configuration report; Exploit protection policy; Device Guard status (msinfo32/Intune). | N84: Windows Enterprise for Credential Guard; MDE for ASR reporting. | O84: ES-2
A85: 10 | B85: Malware Defenses | C85: 10.6 | D85: Centrally Manage Anti-Malware Software | E85: Devices | F85: Protect | H85: ✓ | I85: ✓ | J85: Native | K85: Intune Endpoint security (Antivirus policies); Defender portal (MDE security settings management); Defender for Cloud | L85: Manage all Defender AV settings centrally via Intune or MDE security settings management (covers non-Intune servers). Avoid local overrides (tamper protection, disable local admin merge). Monitor via Defender portal. | M85: Policy assignment reports; tamper protection; local admin merge disabled. | N85: MDE; Intune. | O85: ES-1, ES-3
A86: 10 | B86: Malware Defenses | C86: 10.7 | D86: Use Behavior-Based Anti-Malware Software | E86: Devices | F86: Detect | H86: ✓ | I86: ✓ | J86: Native | K86: Defender for Endpoint EDR (behavioural detections, EDR in block mode, AIR); Defender Antivirus behaviour monitoring & cloud ML; Defender XDR attack disruption | L86: Enable behaviour monitoring, cloud-delivered protection and EDR in block mode; set automated investigation & remediation to Full. Ensure automatic attack disruption is enabled in Defender XDR. | M86: MDE advanced features settings; AIR level; detection examples. | N86: MDE P2 / Defender for Business. | O86: ES-1, LT-1
A87: 11 | B87: Data Recovery | C87: 11.1 | D87: Establish and Maintain a Data Recovery Process | E87: Documentation | F87: Govern | G87: ✓ | H87: ✓ | I87: ✓ | J87: Process | K87: Azure Backup; Azure Site Recovery; Microsoft 365 Backup; Purview retention; Intune/Autopilot for device rebuild | L87: Document backup scope, RPO/RTO by data class, recovery prioritisation and responsibilities, including M365 data (note M365 retention ≠ backup). Map each system to Azure Backup, Microsoft 365 Backup or third-party tool. Review annually. | M87: Data recovery policy; system-to-backup mapping with RPO/RTO. | N87: — | O87: BR-1
A88: 11 | B88: Data Recovery | C88: 11.2 | D88: Perform Automated Backups | E88: Data | F88: Recover | G88: ✓ | H88: ✓ | I88: ✓ | J88: Native | K88: Azure Backup (VMs, SQL, Files, Blobs, AKS, on-prem via MARS/MABS); Microsoft 365 Backup (Exchange, SharePoint, OneDrive); Azure Policy 'Configure backup on VMs' | L88: Use Azure Policy to auto-enrol VMs into Azure Backup with daily (or more frequent) policies. Back up Azure Files, SQL/SAP HANA, Blob (operational + vaulted), AKS. Enable Microsoft 365 Backup (or third-party) for Exchange, SharePoint, OneDrive/Teams. Monitor backup jobs with Backup Center/Business Continuity Center alerts. | M88: Backup policy definitions; job success reports; Azure Policy compliance. | N88: Azure Backup consumption; Microsoft 365 Backup pay-as-you-go. | O88: BR-1, BR-2
A89: 11 | B89: Data Recovery | C89: 11.3 | D89: Protect Recovery Data | E89: Data | F89: Protect | G89: ✓ | H89: ✓ | I89: ✓ | J89: Native | K89: Recovery Services / Backup vault: soft delete (always-on), immutable vaults, multi-user authorization (Resource Guard), CMK encryption, private endpoints; Azure RBAC | L89: Enable immutable vaults (locked), enhanced soft delete, Multi-User Authorization via Resource Guard in a separate tenant/subscription for critical operations, CMK encryption and private endpoints. Restrict Backup Contributor roles via PIM. | M89: Vault security settings; Resource Guard configuration; security level 'Maximum' in Backup Center. | N89: Azure Backup. | O89: BR-2
A90: 11 | B90: Data Recovery | C90: 11.4 | D90: Establish and Maintain an Isolated Instance of Recovery Data | E90: Data | F90: Recover | G90: ✓ | H90: ✓ | I90: ✓ | J90: Native | K90: Azure Backup vaulted tier (logically air-gapped, separate tenant-managed vault), immutable + locked; Cross-region restore; Microsoft 365 Backup (immutable, separate from production); Azure Storage immutability | L90: Keep at least one copy in a vaulted (not snapshot-only) tier with immutability locked and MUA, ideally GRS with Cross Region Restore. Consider a separate subscription/tenant for backup administration. Microsoft 365 Backup stores immutable copies separate from production data. | M90: Vault redundancy and immutability settings; architecture showing isolation. | N90: Azure Backup (GRS costs). | O90: BR-2
A91: 11 | B91: Data Recovery | C91: 11.5 | D91: Test Data Recovery | E91: Data | F91: Recover | H91: ✓ | I91: ✓ | J91: Native | K91: Azure Backup restore (alternate location); Azure Site Recovery test failover; Microsoft 365 Backup restore; Azure Chaos Studio for DR drills | L91: Schedule quarterly (at least) test restores of a sample of in-scope assets: Azure Backup restore to isolated VNet, ASR test failover without production impact, Microsoft 365 Backup restore of a site/mailbox. Record results against RPO/RTO. | M91: Restore test records with outcome and timing. | N91: Consumption of restore resources. | O91: BR-3
A92: 12 | B92: Network Infrastructure Management | C92: 12.1 | D92: Ensure Network Infrastructure is Up-to-Date | E92: Network | F92: Protect | G92: ✓ | H92: ✓ | I92: ✓ | J92: Partial | K92: Azure PaaS network services (Microsoft-managed: Azure Firewall, VPN Gateway, App Gateway, Front Door); DVM network device authenticated scans; vendor firmware management | L92: Azure-native network services are patched by Microsoft; ensure you use supported SKUs (e.g. migrate from Basic SKUs/classic resources). For on-prem/NVA devices, keep firmware on vendor-supported versions and scan with DVM network device assessment monthly. | M92: SKU review; DVM network device findings; firmware register. | N92: DVM add-on. | O92: PV-6, PV-7
A93: 12 | B93: Network Infrastructure Management | C93: 12.2 | D93: Establish and Maintain a Secure Network Architecture | E93: Network | F93: Govern | H93: ✓ | I93: ✓ | J93: Native | K93: Azure landing zones (Cloud Adoption Framework) with hub-spoke / Virtual WAN; Azure Firewall; Private Link; DDoS Protection; Entra Global Secure Access (Zero Trust network access) | L93: Design network per CAF landing zone: segmented hub-spoke/vWAN, centralised inspection with Azure Firewall, private endpoints for PaaS, DDoS Network Protection on public endpoints, no direct internet on management. Move user access to Zero Trust (Entra Private/Internet Access). Document segmentation, least privilege and availability. | M93: Network architecture document; Azure Policy landing zone compliance. | N93: Azure Firewall/DDoS/GSA licences. | O93: NS-1, NS-2, NS-5
A94: 12 | B94: Network Infrastructure Management | C94: 12.3 | D94: Securely Manage Network Infrastructure | E94: Network | F94: Protect | H94: ✓ | I94: ✓ | J94: Native | K94: IaC (Bicep/Terraform) with Git version control and PR approvals; Azure Firewall Manager; Azure Bastion; Azure RBAC/PIM for Network Contributor | L94: Manage Azure networking only through version-controlled IaC pipelines with approvals; lock resources and restrict Network Contributor via PIM. Use secure protocols (HTTPS, SSH) and Bastion for device management. For on-prem gear, keep configs in version control. | M94: IaC repo history; PIM role assignments; resource locks. | N94: Entra ID P2 for PIM. | O94: NS-1, DS-6, PA-2
A95: 12 | B95: Network Infrastructure Management | C95: 12.4 | D95: Establish and Maintain Architecture Diagram(s) | E95: Documentation | F95: Govern | H95: ✓ | I95: ✓ | J95: Partial | K95: Azure Network Watcher topology; Visio / draw.io; Defender CSPM cloud security explorer; Azure Resource Graph | L95: Maintain logical and physical network diagrams (generated from Network Watcher topology and enriched manually) in a controlled library; review annually or on significant change. | M95: Current dated diagrams with version history. | N95: — | O95: NS-1, GS-3
A96: 12 | B96: Network Infrastructure Management | C96: 12.5 | D96: Centralize Network Authentication, Authorization, and Auditing (AAA) | E96: Network | F96: Protect | H96: ✓ | I96: ✓ | J96: Native | K96: Entra ID (SAML/OIDC for network device consoles); NPS + Entra MFA extension for RADIUS; Azure RBAC for cloud network control plane; Sentinel for audit | L96: Authenticate network device administration centrally via RADIUS/TACACS+ backed by AD/NPS with Entra MFA, or SAML to Entra where the vendor supports it. Azure control plane is centralised through Entra/Azure RBAC. Forward AAA logs to Sentinel. | M96: AAA configuration; device admin sign-in logs in Sentinel. | N96: Entra ID P1. | O96: NS-1, IM-1
A97: 12 | B97: Network Infrastructure Management | C97: 12.6 | D97: Use of Secure Network Management and Communication Protocols | E97: Network | F97: Protect | H97: ✓ | I97: ✓ | J97: Native | K97: WPA2/WPA3-Enterprise Wi-Fi with EAP-TLS (Intune certificate profiles, Cloud PKI); Azure policies enforcing TLS 1.2+, SSH; SNMPv3 on devices | L97: Use 802.1X EAP-TLS Wi-Fi with device certs issued via Intune (Cloud PKI/SCEP/PKCS). Disable Telnet, HTTP, SNMPv1/2c management. Enforce TLS 1.2+ for Azure services via policy. | M97: Intune Wi-Fi & cert profiles; device config standard; Azure Policy report. | N97: Intune Cloud PKI needs Intune Suite/add-on. | O97: NS-1, DP-3
A98: 12 | B98: Network Infrastructure Management | C98: 12.7 | D98: Ensure Remote Devices Utilize a VPN and are Connecting to an Enterprise's AAA Infrastructure | E98: Devices | F98: Protect | H98: ✓ | I98: ✓ | J98: Native | K98: Microsoft Entra Private Access / Global Secure Access client; Azure VPN Gateway P2S with Entra auth; Always On VPN; Conditional Access (compliant device) | L98: Require remote users to reach private resources via Entra Private Access or VPN authenticated by Entra ID/AD with MFA and device compliance. Deploy GSA client / Always On VPN profile via Intune. | M98: GSA/VPN Intune profile; CA policy; connection logs. | N98: Entra Private Access licence; Entra ID P1. | O98: NS-1, IM-7
A99: 12 | B99: Network Infrastructure Management | C99: 12.8 | D99: Establish and Maintain Dedicated Computing Resources for All Administrative Work | E99: Devices | F99: Protect | I99: ✓ | J99: Native | K99: Privileged Access Workstations (Intune PAW profiles); Windows 365 / Azure Virtual Desktop admin workstations; Conditional Access device filters; Azure Bastion | L99: Build PAWs (or hardened Windows 365 Cloud PCs) for administrators with restricted apps, no email/web browsing, App Control enforced. Use Conditional Access device filters so admin roles and Azure management can only be accessed from PAW devices. No Internet browsing from admin sessions. | M99: PAW Intune configuration; CA policy restricting admin roles to PAW. | N99: Intune; Windows 365 licences; Entra ID P1. | O99: PA-6
A100: 13 | B100: Network Monitoring and Defense | C100: 13.1 | D100: Centralize Security Event Alerting | E100: Network | F100: Detect | H100: ✓ | I100: ✓ | J100: Native | K100: Microsoft Defender XDR (unified incidents) + Microsoft Sentinel (SIEM); Defender for Cloud alerts streamed | L100: Connect Defender XDR, Defender for Cloud and third-party sources to Sentinel in the unified Defender portal so all alerts correlate into incidents. Enable incident notifications/automation (playbooks) and define on-call routing. | M100: Unified portal incident queue; connector list; notification rules. | N100: Sentinel; Defender XDR licences. | O100: LT-1, LT-5, IR-2
...
